Workbook

Sheet activos
A2: MATRIZ | C2: ESPECIFICA | E2: SUB ESPECIFICA | G2: PUBLICACION 21 | I2: TERCER DIGITO DE PUB 21 Y | K2: SUB ESPECIFICA DE PUB 21 | M2: CUENTA MATRIZ | O2: AUXILIAR DE PUB 21
A3: cod | B3: DENOMINACION | C3: cod | D3: DENOMINACION | E3: cod | F3: DENOMINACION | G3: cod | H3: DENOMINACION | I3: cod | J3: DENOMINACION | K3: cod | L3: DENOMINACION | M3: CODIGO UNIFICADO | N3: DENOMINACION DE LA CUENTA | O3: cod | P3: DENOMINACION | Q3: CODIGO UNIFICADO | R3: DENOMINACION DE LA CUENTA | S3: =CONCATENATE(TEXT(LEFT(G3,2),"00"),"-",TEXT(RIGHT(G3,1),"0")) -> co-d
A4: 1 | B4: =VLOOKUP(A4,'ACTIVOS CODIGO'!A:B,2,0) -> ACTIVO | G4: 0 | M4: =CONCATENATE(TEXT(A4,"0"),"-",TEXT(C4,"0"),"-",TEXT(E4,"0"),"-",TEXT(LEFT(G4,2),"00"),"-",TEXT(RIGHT(G4,1),"0"),TEXT(I4,"0"),"-",TEXT(K4,"00")) -> 1-0-0-00-00-00 | N4: =IF(L4="",IF(J4="",IF(H4="",IF(F4="",IF(D4="",B4,D4),F4),H4),J4),L4) -> ACTIVO | O4: =IF(P4="",0,IF(M3=M4,IF(O3="",0,O3)+1,"")) -> 0 | Q4: =CONCATENATE(TEXT(A4,"0"),"-",TEXT(C4,"0"),"-",TEXT(E4,"0"),"-",TEXT(LEFT(G4,2),"00"),"-",TEXT(RIGHT(G4,1),"0"),TEXT(I4,"0"),"-",TEXT(K4,"00"),"-",TEXT(O4,"000")) -> 1-0-0-00-00-00-000 | R4: =IF(P4="",IF(L4="",IF(J4="",IF(H4="",IF(F4="",IF(D4="",B4,D4),F4),H4),J4),L4),P4) -> ACTIVO | S4: =CONCATENATE(TEXT(LEFT(G4,2),"00"),"-",TEXT(RIGHT(G4,1),"0")) -> 00-0
A5: 1 | B5: =VLOOKUP(A5,'ACTIVOS CODIGO'!A:B,2,0) -> ACTIVO | C5: 1 | D5: =VLOOKUP(C5,'ACTIVOS CODIGO'!C:D,2,0) -> ACTIVO DEL TESORO = ACTIVO CORRIENTE | G5: 0 | M5: =CONCATENATE(TEXT(A5,"0"),"-",TEXT(C5,"0"),"-",TEXT(E5,"0"),"-",TEXT(LEFT(G5,2),"00"),"-",TEXT(RIGHT(G5,1),"0"),TEXT(I5,"0"),"-",TEXT(K5,"00")) -> 1-1-0-00-00-00 | N5: =IF(L5="",IF(J5="",IF(H5="",IF(F5="",IF(D5="",B5,D5),F5),H5),J5),L5) -> ACTIVO DEL TESORO = ACTIVO CORRIENTE | O5: =IF(P5="",0,IF(M4=M5,IF(O4="",0,O4)+1,"")) -> 0 | Q5: =CONCATENATE(TEXT(A5,"0"),"-",TEXT(C5,"0"),"-",TEXT(E5,"0"),"-",TEXT(LEFT(G5,2),"00"),"-",TEXT(RIGHT(G5,1),"0"),TEXT(I5,"0"),"-",TEXT(K5,"00"),"-",TEXT(O5,"000")) -> 1-1-0-00-00-00-000 | R5: =IF(P5="",IF(L5="",IF(J5="",IF(H5="",IF(F5="",IF(D5="",B5,D5),F5),H5),J5),L5),P5) -> ACTIVO DEL TESORO = ACTIVO CORRIENTE | S5: =CONCATENATE(TEXT(LEFT(G5,2),"00"),"-",TEXT(RIGHT(G5,1),"0")) -> 00-0 | T5: ACTIVO CORRIENTE | U5: 100
A6: 1 | B6: =VLOOKUP(A6,'ACTIVOS CODIGO'!A:B,2,0) -> ACTIVO | C6: 1 | D6: =VLOOKUP(C6,'ACTIVOS CODIGO'!C:D,2,0) -> ACTIVO DEL TESORO = ACTIVO CORRIENTE | E6: 1 | F6: =VLOOKUP(E6,'ACTIVOS CODIGO'!E:F,2,0) -> ACTIVO DISPONIBLE | G6: 0 | M6: =CONCATENATE(TEXT(A6,"0"),"-",TEXT(C6,"0"),"-",TEXT(E6,"0"),"-",TEXT(LEFT(G6,2),"00"),"-",TEXT(RIGHT(G6,1),"0"),TEXT(I6,"0"),"-",TEXT(K6,"00")) -> 1-1-1-00-00-00 | N6: =IF(L6="",IF(J6="",IF(H6="",IF(F6="",IF(D6="",B6,D6),F6),H6),J6),L6) -> ACTIVO DISPONIBLE | O6: =IF(P6="",0,IF(M5=M6,IF(O5="",0,O5)+1,"")) -> 0 | Q6: =CONCATENATE(TEXT(A6,"0"),"-",TEXT(C6,"0"),"-",TEXT(E6,"0"),"-",TEXT(LEFT(G6,2),"00"),"-",TEXT(RIGHT(G6,1),"0"),TEXT(I6,"0"),"-",TEXT(K6,"00"),"-",TEXT(O6,"000")) -> 1-1-1-00-00-00-000 | R6: =IF(P6="",IF(L6="",IF(J6="",IF(H6="",IF(F6="",IF(D6="",B6,D6),F6),H6),J6),L6),P6) -> ACTIVO DISPONIBLE | S6: =CONCATENATE(TEXT(LEFT(G6,2),"00"),"-",TEXT(RIGHT(G6,1),"0")) -> 00-0
A7: 1 | B7: =VLOOKUP(A7,'ACTIVOS CODIGO'!A:B,2,0) -> ACTIVO | C7: 1 | D7: =VLOOKUP(C7,'ACTIVOS CODIGO'!C:D,2,0) -> ACTIVO DEL TESORO = ACTIVO CORRIENTE | E7: 1 | F7: =VLOOKUP(E7,'ACTIVOS CODIGO'!E:F,2,0) -> ACTIVO DISPONIBLE | G7: 102 | H7: =VLOOKUP(G7,'PUB 21'!$A$1:$B$29,2,0) -> TESORERIA MUNICIPAL | M7: =CONCATENATE(TEXT(A7,"0"),"-",TEXT(C7,"0"),"-",TEXT(E7,"0"),"-",TEXT(LEFT(G7,2),"00"),"-",TEXT(RIGHT(G7,1),"0"),TEXT(I7,"0"),"-",TEXT(K7,"00")) -> 1-1-1-10-20-00 | N7: =IF(L7="",IF(J7="",IF(H7="",IF(F7="",IF(D7="",B7,D7),F7),H7),J7),L7) -> TESORERIA MUNICIPAL | O7: =IF(P7="",0,IF(M6=M7,IF(O6="",0,O6)+1,"")) -> 0 | Q7: =CONCATENATE(TEXT(A7,"0"),"-",TEXT(C7,"0"),"-",TEXT(E7,"0"),"-",TEXT(LEFT(G7,2),"00"),"-",TEXT(RIGHT(G7,1),"0"),TEXT(I7,"0"),"-",TEXT(K7,"00"),"-",TEXT(O7,"000")) -> 1-1-1-10-20-00-000 | R7: =IF(P7="",IF(L7="",IF(J7="",IF(H7="",IF(F7="",IF(D7="",B7,D7),F7),H7),J7),L7),P7) -> TESORERIA MUNICIPAL | S7: =CONCATENATE(TEXT(LEFT(G7,2),"00"),"-",TEXT(RIGHT(G7,1),"0")) -> 10-2 | T7: TESORERIA MUNICIPAL | U7: 102
A8: 1 | B8: =VLOOKUP(A8,'ACTIVOS CODIGO'!A:B,2,0) -> ACTIVO | C8: 1 | D8: =VLOOKUP(C8,'ACTIVOS CODIGO'!C:D,2,0) -> ACTIVO DEL TESORO = ACTIVO CORRIENTE | E8: 1 | F8: =VLOOKUP(E8,'ACTIVOS CODIGO'!E:F,2,0) -> ACTIVO DISPONIBLE | G8: 102 | H8: =VLOOKUP(G8,'PUB 21'!$A$1:$B$29,2,0) -> TESORERIA MUNICIPAL | I8: 1 | J8: BANCOS PUBLICOS Y PRIVADOS | M8: =CONCATENATE(TEXT(A8,"0"),"-",TEXT(C8,"0"),"-",TEXT(E8,"0"),"-",TEXT(LEFT(G8,2),"00"),"-",TEXT(RIGHT(G8,1),"0"),TEXT(I8,"0"),"-",TEXT(K8,"00")) -> 1-1-1-10-21-00 | N8: =IF(L8="",IF(J8="",IF(H8="",IF(F8="",IF(D8="",B8,D8),F8),H8),J8),L8) -> BANCOS PUBLICOS Y PRIVADOS | O8: =IF(P8="",0,IF(M7=M8,IF(O7="",0,O7)+1,"")) -> 0 | Q8: =CONCATENATE(TEXT(A8,"0"),"-",TEXT(C8,"0"),"-",TEXT(E8,"0"),"-",TEXT(LEFT(G8,2),"00"),"-",TEXT(RIGHT(G8,1),"0"),TEXT(I8,"0"),"-",TEXT(K8,"00"),"-",TEXT(O8,"000")) -> 1-1-1-10-21-00-000 | R8: =IF(P8="",IF(L8="",IF(J8="",IF(H8="",IF(F8="",IF(D8="",B8,D8),F8),H8),J8),L8),P8) -> BANCOS PUBLICOS Y PRIVADOS | T8: BANCOS PUBLICOS Y PRIVADOS | U8: 102
A9: 1 | B9: =VLOOKUP(A9,'ACTIVOS CODIGO'!A:B,2,0) -> ACTIVO | C9: 1 | D9: =VLOOKUP(C9,'ACTIVOS CODIGO'!C:D,2,0) -> ACTIVO DEL TESORO = ACTIVO CORRIENTE | E9: 1 | F9: =VLOOKUP(E9,'ACTIVOS CODIGO'!E:F,2,0) -> ACTIVO DISPONIBLE | G9: 102 | H9: =VLOOKUP(G9,'PUB 21'!$A$1:$B$29,2,0) -> TESORERIA MUNICIPAL | I9: 1 | J9: BANCOS PUBLICOS Y PRIVADOS | K9: 1 | L9: BANCO PUBLICO | M9: =CONCATENATE(TEXT(A9,"0"),"-",TEXT(C9,"0"),"-",TEXT(E9,"0"),"-",TEXT(LEFT(G9,2),"00"),"-",TEXT(RIGHT(G9,1),"0"),TEXT(I9,"0"),"-",TEXT(K9,"00")) -> 1-1-1-10-21-01 | N9: =IF(L9="",IF(J9="",IF(H9="",IF(F9="",IF(D9="",B9,D9),F9),H9),J9),L9) -> BANCO PUBLICO | O9: =IF(P9="",0,IF(M8=M9,IF(O8="",0,O8)+1,"")) -> 0 | Q9: =CONCATENATE(TEXT(A9,"0"),"-",TEXT(C9,"0"),"-",TEXT(E9,"0"),"-",TEXT(LEFT(G9,2),"00"),"-",TEXT(RIGHT(G9,1),"0"),TEXT(I9,"0"),"-",TEXT(K9,"00"),"-",TEXT(O9,"000")) -> 1-1-1-10-21-01-000 | R9: =IF(P9="",IF(L9="",IF(J9="",IF(H9="",IF(F9="",IF(D9="",B9,D9),F9),H9),J9),L9),P9) -> BANCO PUBLICO
A10: 1 | B10: =VLOOKUP(A10,'ACTIVOS CODIGO'!A:B,2,0) -> ACTIVO | C10: 1 | D10: =VLOOKUP(C10,'ACTIVOS CODIGO'!C:D,2,0) -> ACTIVO DEL TESORO = ACTIVO CORRIENTE | E10: 1 | F10: =VLOOKUP(E10,'ACTIVOS CODIGO'!E:F,2,0) -> ACTIVO DISPONIBLE | G10: 102 | H10: =VLOOKUP(G10,'PUB 21'!$A$1:$B$29,2,0) -> TESORERIA MUNICIPAL | I10: 1 | J10: BANCOS PUBLICOS Y PRIVADOS | K10: 1 | L10: BANCO PUBLICO | M10: =CONCATENATE(TEXT(A10,"0"),"-",TEXT(C10,"0"),"-",TEXT(E10,"0"),"-",TEXT(LEFT(G10,2),"00"),"-",TEXT(RIGHT(G10,1),"0"),TEXT(I10,"0"),"-",TEXT(K10,"00")) -> 1-1-1-10-21-01 | N10: =IF(L10="",IF(J10="",IF(H10="",IF(F10="",IF(D10="",B10,D10),F10),H10),J10),L10) -> BANCO PUBLICO | O10: =IF(P10="",0,IF(M9=M10,IF(O9="",0,O9)+1,"")) -> 1 | P10: I.M.C.P. 0601-0001-24-0014071948 | Q10: =CONCATENATE(TEXT(A10,"0"),"-",TEXT(C10,"0"),"-",TEXT(E10,"0"),"-",TEXT(LEFT(G10,2),"00"),"-",TEXT(RIGHT(G10,1),"0"),TEXT(I10,"0"),"-",TEXT(K10,"00"),"-",TEXT(O10,"000")) -> 1-1-1-10-21-01-001 | R10: =IF(P10="",IF(L10="",IF(J10="",IF(H10="",IF(F10="",IF(D10="",B10,D10),F10),H10),J10),L10),P10) -> I.M.C.P. 0601-0001-24-0014071948
A11: 1 | B11: =VLOOKUP(A11,'ACTIVOS CODIGO'!A:B,2,0) -> ACTIVO | C11: 1 | D11: =VLOOKUP(C11,'ACTIVOS CODIGO'!C:D,2,0) -> ACTIVO DEL TESORO = ACTIVO CORRIENTE | E11: 1 | F11: =VLOOKUP(E11,'ACTIVOS CODIGO'!E:F,2,0) -> ACTIVO DISPONIBLE | G11: 102 | H11: =VLOOKUP(G11,'PUB 21'!$A$1:$B$29,2,0) -> TESORERIA MUNICIPAL | I11: 1 | J11: BANCOS PUBLICOS Y PRIVADOS | K11: 1 | L11: BANCO PUBLICO | M11: =CONCATENATE(TEXT(A11,"0"),"-",TEXT(C11,"0"),"-",TEXT(E11,"0"),"-",TEXT(LEFT(G11,2),"00"),"-",TEXT(RIGHT(G11,1),"0"),TEXT(I11,"0"),"-",TEXT(K11,"00")) -> 1-1-1-10-21-01 | N11: =IF(L11="",IF(J11="",IF(H11="",IF(F11="",IF(D11="",B11,D11),F11),H11),J11),L11) -> BANCO PUBLICO | O11: =IF(P11="",0,IF(M10=M11,IF(O10="",0,O10)+1,"")) -> 2 | P11: VENEZUELA 0102-0762-200000039709 | Q11: =CONCATENATE(TEXT(A11,"0"),"-",TEXT(C11,"0"),"-",TEXT(E11,"0"),"-",TEXT(LEFT(G11,2),"00"),"-",TEXT(RIGHT(G11,1),"0"),TEXT(I11,"0"),"-",TEXT(K11,"00"),"-",TEXT(O11,"000")) -> 1-1-1-10-21-01-002 | R11: =IF(P11="",IF(L11="",IF(J11="",IF(H11="",IF(F11="",IF(D11="",B11,D11),F11),H11),J11),L11),P11) -> VENEZUELA 0102-0762-200000039709
A12: 1 | B12: =VLOOKUP(A12,'ACTIVOS CODIGO'!A:B,2,0) -> ACTIVO | C12: 1 | D12: =VLOOKUP(C12,'ACTIVOS CODIGO'!C:D,2,0) -> ACTIVO DEL TESORO = ACTIVO CORRIENTE | E12: 1 | F12: =VLOOKUP(E12,'ACTIVOS CODIGO'!E:F,2,0) -> ACTIVO DISPONIBLE | G12: 102 | H12: =VLOOKUP(G12,'PUB 21'!$A$1:$B$29,2,0) -> TESORERIA MUNICIPAL | I12: 1 | J12: BANCOS PUBLICOS Y PRIVADOS | K12: 1 | L12: BANCO PUBLICO | M12: =CONCATENATE(TEXT(A12,"0"),"-",TEXT(C12,"0"),"-",TEXT(E12,"0"),"-",TEXT(LEFT(G12,2),"00"),"-",TEXT(RIGHT(G12,1),"0"),TEXT(I12,"0"),"-",TEXT(K12,"00")) -> 1-1-1-10-21-01 | N12: =IF(L12="",IF(J12="",IF(H12="",IF(F12="",IF(D12="",B12,D12),F12),H12),J12),L12) -> BANCO PUBLICO | O12: =IF(P12="",0,IF(M11=M12,IF(O11="",0,O11)+1,"")) -> 3 | P12: TESORO 0163-0903-65-9033005695 | Q12: =CONCATENATE(TEXT(A12,"0"),"-",TEXT(C12,"0"),"-",TEXT(E12,"0"),"-",TEXT(LEFT(G12,2),"00"),"-",TEXT(RIGHT(G12,1),"0"),TEXT(I12,"0"),"-",TEXT(K12,"00"),"-",TEXT(O12,"000")) -> 1-1-1-10-21-01-003 | R12: =IF(P12="",IF(L12="",IF(J12="",IF(H12="",IF(F12="",IF(D12="",B12,D12),F12),H12),J12),L12),P12) -> TESORO 0163-0903-65-9033005695
A13: 1 | B13: =VLOOKUP(A13,'ACTIVOS CODIGO'!A:B,2,0) -> ACTIVO | C13: 1 | D13: =VLOOKUP(C13,'ACTIVOS CODIGO'!C:D,2,0) -> ACTIVO DEL TESORO = ACTIVO CORRIENTE | E13: 1 | F13: =VLOOKUP(E13,'ACTIVOS CODIGO'!E:F,2,0) -> ACTIVO DISPONIBLE | G13: 102 | H13: =VLOOKUP(G13,'PUB 21'!$A$1:$B$29,2,0) -> TESORERIA MUNICIPAL | I13: 1 | J13: BANCOS PUBLICOS Y PRIVADOS | K13: 1 | L13: BANCO PUBLICO | M13: =CONCATENATE(TEXT(A13,"0"),"-",TEXT(C13,"0"),"-",TEXT(E13,"0"),"-",TEXT(LEFT(G13,2),"00"),"-",TEXT(RIGHT(G13,1),"0"),TEXT(I13,"0"),"-",TEXT(K13,"00")) -> 1-1-1-10-21-01 | N13: =IF(L13="",IF(J13="",IF(H13="",IF(F13="",IF(D13="",B13,D13),F13),H13),J13),L13) -> BANCO PUBLICO | O13: =IF(P13="",0,IF(M12=M13,IF(O12="",0,O12)+1,"")) -> 4 | P13: VENEZUELA 0000059226 | Q13: =CONCATENATE(TEXT(A13,"0"),"-",TEXT(C13,"0"),"-",TEXT(E13,"0"),"-",TEXT(LEFT(G13,2),"00"),"-",TEXT(RIGHT(G13,1),"0"),TEXT(I13,"0"),"-",TEXT(K13,"00"),"-",TEXT(O13,"000")) -> 1-1-1-10-21-01-004 | R13: =IF(P13="",IF(L13="",IF(J13="",IF(H13="",IF(F13="",IF(D13="",B13,D13),F13),H13),J13),L13),P13) -> VENEZUELA 0000059226
A14: 1 | B14: =VLOOKUP(A14,'ACTIVOS CODIGO'!A:B,2,0) -> ACTIVO | C14: 1 | D14: =VLOOKUP(C14,'ACTIVOS CODIGO'!C:D,2,0) -> ACTIVO DEL TESORO = ACTIVO CORRIENTE | E14: 1 | F14: =VLOOKUP(E14,'ACTIVOS CODIGO'!E:F,2,0) -> ACTIVO DISPONIBLE | G14: 102 | H14: =VLOOKUP(G14,'PUB 21'!$A$1:$B$29,2,0) -> TESORERIA MUNICIPAL | I14: 1 | J14: BANCOS PUBLICOS Y PRIVADOS | K14: 1 | L14: BANCO PUBLICO | M14: =CONCATENATE(TEXT(A14,"0"),"-",TEXT(C14,"0"),"-",TEXT(E14,"0"),"-",TEXT(LEFT(G14,2),"00"),"-",TEXT(RIGHT(G14,1),"0"),TEXT(I14,"0"),"-",TEXT(K14,"00")) -> 1-1-1-10-21-01 | N14: =IF(L14="",IF(J14="",IF(H14="",IF(F14="",IF(D14="",B14,D14),F14),H14),J14),L14) -> BANCO PUBLICO | O14: =IF(P14="",0,IF(M13=M14,IF(O13="",0,O13)+1,"")) -> 5 | P14: I.M.C.P. 0014103444 CTA. GTOS. 2021 | Q14: =CONCATENATE(TEXT(A14,"0"),"-",TEXT(C14,"0"),"-",TEXT(E14,"0"),"-",TEXT(LEFT(G14,2),"00"),"-",TEXT(RIGHT(G14,1),"0"),TEXT(I14,"0"),"-",TEXT(K14,"00"),"-",TEXT(O14,"000")) -> 1-1-1-10-21-01-005 | R14: =IF(P14="",IF(L14="",IF(J14="",IF(H14="",IF(F14="",IF(D14="",B14,D14),F14),H14),J14),L14),P14) -> I.M.C.P. 0014103444 CTA. GTOS. 2021
A15: 1 | B15: =VLOOKUP(A15,'ACTIVOS CODIGO'!A:B,2,0) -> ACTIVO | C15: 1 | D15: =VLOOKUP(C15,'ACTIVOS CODIGO'!C:D,2,0) -> ACTIVO DEL TESORO = ACTIVO CORRIENTE | E15: 1 | F15: =VLOOKUP(E15,'ACTIVOS CODIGO'!E:F,2,0) -> ACTIVO DISPONIBLE | G15: 102 | H15: =VLOOKUP(G15,'PUB 21'!$A$1:$B$29,2,0) -> TESORERIA MUNICIPAL | I15: 1 | J15: BANCOS PUBLICOS Y PRIVADOS | K15: 1 | L15: BANCO PUBLICO | M15: =CONCATENATE(TEXT(A15,"0"),"-",TEXT(C15,"0"),"-",TEXT(E15,"0"),"-",TEXT(LEFT(G15,2),"00"),"-",TEXT(RIGHT(G15,1),"0"),TEXT(I15,"0"),"-",TEXT(K15,"00")) -> 1-1-1-10-21-01 | N15: =IF(L15="",IF(J15="",IF(H15="",IF(F15="",IF(D15="",B15,D15),F15),H15),J15),L15) -> BANCO PUBLICO | O15: =IF(P15="",0,IF(M14=M15,IF(O14="",0,O14)+1,"")) -> 6 | P15: IMCP 0014103451 FISCO MCPAL. 2021 | Q15: =CONCATENATE(TEXT(A15,"0"),"-",TEXT(C15,"0"),"-",TEXT(E15,"0"),"-",TEXT(LEFT(G15,2),"00"),"-",TEXT(RIGHT(G15,1),"0"),TEXT(I15,"0"),"-",TEXT(K15,"00"),"-",TEXT(O15,"000")) -> 1-1-1-10-21-01-006 | R15: =IF(P15="",IF(L15="",IF(J15="",IF(H15="",IF(F15="",IF(D15="",B15,D15),F15),H15),J15),L15),P15) -> IMCP 0014103451 FISCO MCPAL. 2021
A16: 1 | B16: =VLOOKUP(A16,'ACTIVOS CODIGO'!A:B,2,0) -> ACTIVO | C16: 1 | D16: =VLOOKUP(C16,'ACTIVOS CODIGO'!C:D,2,0) -> ACTIVO DEL TESORO = ACTIVO CORRIENTE | E16: 1 | F16: =VLOOKUP(E16,'ACTIVOS CODIGO'!E:F,2,0) -> ACTIVO DISPONIBLE | G16: 102 | H16: =VLOOKUP(G16,'PUB 21'!$A$1:$B$29,2,0) -> TESORERIA MUNICIPAL | I16: 1 | J16: BANCOS PUBLICOS Y PRIVADOS | K16: 1 | L16: BANCO PUBLICO | M16: =CONCATENATE(TEXT(A16,"0"),"-",TEXT(C16,"0"),"-",TEXT(E16,"0"),"-",TEXT(LEFT(G16,2),"00"),"-",TEXT(RIGHT(G16,1),"0"),TEXT(I16,"0"),"-",TEXT(K16,"00")) -> 1-1-1-10-21-01 | N16: =IF(L16="",IF(J16="",IF(H16="",IF(F16="",IF(D16="",B16,D16),F16),H16),J16),L16) -> BANCO PUBLICO | O16: =IF(P16="",0,IF(M15=M16,IF(O15="",0,O15)+1,"")) -> 7 | P16: I.M.C.P. 0601-0001-28-0014103519 IMP. Y RETENC. 2021 | Q16: =CONCATENATE(TEXT(A16,"0"),"-",TEXT(C16,"0"),"-",TEXT(E16,"0"),"-",TEXT(LEFT(G16,2),"00"),"-",TEXT(RIGHT(G16,1),"0"),TEXT(I16,"0"),"-",TEXT(K16,"00"),"-",TEXT(O16,"000")) -> 1-1-1-10-21-01-007 | R16: =IF(P16="",IF(L16="",IF(J16="",IF(H16="",IF(F16="",IF(D16="",B16,D16),F16),H16),J16),L16),P16) -> I.M.C.P. 0601-0001-28-0014103519 IMP. Y RETENC. 2021
A17: 1 | B17: =VLOOKUP(A17,'ACTIVOS CODIGO'!A:B,2,0) -> ACTIVO | C17: 1 | D17: =VLOOKUP(C17,'ACTIVOS CODIGO'!C:D,2,0) -> ACTIVO DEL TESORO = ACTIVO CORRIENTE | E17: 1 | F17: =VLOOKUP(E17,'ACTIVOS CODIGO'!E:F,2,0) -> ACTIVO DISPONIBLE | G17: 102 | H17: =VLOOKUP(G17,'PUB 21'!$A$1:$B$29,2,0) -> TESORERIA MUNICIPAL | I17: 1 | J17: BANCOS PUBLICOS Y PRIVADOS | K17: 1 | L17: BANCO PUBLICO | M17: =CONCATENATE(TEXT(A17,"0"),"-",TEXT(C17,"0"),"-",TEXT(E17,"0"),"-",TEXT(LEFT(G17,2),"00"),"-",TEXT(RIGHT(G17,1),"0"),TEXT(I17,"0"),"-",TEXT(K17,"00")) -> 1-1-1-10-21-01 | N17: =IF(L17="",IF(J17="",IF(H17="",IF(F17="",IF(D17="",B17,D17),F17),H17),J17),L17) -> BANCO PUBLICO | O17: =IF(P17="",0,IF(M16=M17,IF(O16="",0,O16)+1,"")) -> 8 | P17: I.M.C.P. 0014103501 RESERVAS 2021 | Q17: =CONCATENATE(TEXT(A17,"0"),"-",TEXT(C17,"0"),"-",TEXT(E17,"0"),"-",TEXT(LEFT(G17,2),"00"),"-",TEXT(RIGHT(G17,1),"0"),TEXT(I17,"0"),"-",TEXT(K17,"00"),"-",TEXT(O17,"000")) -> 1-1-1-10-21-01-008 | R17: =IF(P17="",IF(L17="",IF(J17="",IF(H17="",IF(F17="",IF(D17="",B17,D17),F17),H17),J17),L17),P17) -> I.M.C.P. 0014103501 RESERVAS 2021
A18: 1 | B18: =VLOOKUP(A18,'ACTIVOS CODIGO'!A:B,2,0) -> ACTIVO | C18: 1 | D18: =VLOOKUP(C18,'ACTIVOS CODIGO'!C:D,2,0) -> ACTIVO DEL TESORO = ACTIVO CORRIENTE | E18: 1 | F18: =VLOOKUP(E18,'ACTIVOS CODIGO'!E:F,2,0) -> ACTIVO DISPONIBLE | G18: 102 | H18: =VLOOKUP(G18,'PUB 21'!$A$1:$B$29,2,0) -> TESORERIA MUNICIPAL | I18: 1 | J18: BANCOS PUBLICOS Y PRIVADOS | K18: 1 | L18: BANCO PUBLICO | M18: =CONCATENATE(TEXT(A18,"0"),"-",TEXT(C18,"0"),"-",TEXT(E18,"0"),"-",TEXT(LEFT(G18,2),"00"),"-",TEXT(RIGHT(G18,1),"0"),TEXT(I18,"0"),"-",TEXT(K18,"00")) -> 1-1-1-10-21-01 | N18: =IF(L18="",IF(J18="",IF(H18="",IF(F18="",IF(D18="",B18,D18),F18),H18),J18),L18) -> BANCO PUBLICO | O18: =IF(P18="",0,IF(M17=M18,IF(O17="",0,O17)+1,"")) -> 9 | P18: I.M.C.P 0014103485 APOSTILLAMIENTO 2021 | Q18: =CONCATENATE(TEXT(A18,"0"),"-",TEXT(C18,"0"),"-",TEXT(E18,"0"),"-",TEXT(LEFT(G18,2),"00"),"-",TEXT(RIGHT(G18,1),"0"),TEXT(I18,"0"),"-",TEXT(K18,"00"),"-",TEXT(O18,"000")) -> 1-1-1-10-21-01-009 | R18: =IF(P18="",IF(L18="",IF(J18="",IF(H18="",IF(F18="",IF(D18="",B18,D18),F18),H18),J18),L18),P18) -> I.M.C.P 0014103485 APOSTILLAMIENTO 2021
A19: 1 | B19: =VLOOKUP(A19,'ACTIVOS CODIGO'!A:B,2,0) -> ACTIVO | C19: 1 | D19: =VLOOKUP(C19,'ACTIVOS CODIGO'!C:D,2,0) -> ACTIVO DEL TESORO = ACTIVO CORRIENTE | E19: 1 | F19: =VLOOKUP(E19,'ACTIVOS CODIGO'!E:F,2,0) -> ACTIVO DISPONIBLE | G19: 102 | H19: =VLOOKUP(G19,'PUB 21'!$A$1:$B$29,2,0) -> TESORERIA MUNICIPAL | I19: 1 | J19: BANCOS PUBLICOS Y PRIVADOS | K19: 1 | L19: BANCO PUBLICO | M19: =CONCATENATE(TEXT(A19,"0"),"-",TEXT(C19,"0"),"-",TEXT(E19,"0"),"-",TEXT(LEFT(G19,2),"00"),"-",TEXT(RIGHT(G19,1),"0"),TEXT(I19,"0"),"-",TEXT(K19,"00")) -> 1-1-1-10-21-01 | N19: =IF(L19="",IF(J19="",IF(H19="",IF(F19="",IF(D19="",B19,D19),F19),H19),J19),L19) -> BANCO PUBLICO | O19: =IF(P19="",0,IF(M18=M19,IF(O18="",0,O18)+1,"")) -> 10 | P19: I.M.C.P. 0014103493 FCI 2021 | Q19: =CONCATENATE(TEXT(A19,"0"),"-",TEXT(C19,"0"),"-",TEXT(E19,"0"),"-",TEXT(LEFT(G19,2),"00"),"-",TEXT(RIGHT(G19,1),"0"),TEXT(I19,"0"),"-",TEXT(K19,"00"),"-",TEXT(O19,"000")) -> 1-1-1-10-21-01-010 | R19: =IF(P19="",IF(L19="",IF(J19="",IF(H19="",IF(F19="",IF(D19="",B19,D19),F19),H19),J19),L19),P19) -> I.M.C.P. 0014103493 FCI 2021
A20: 1 | B20: =VLOOKUP(A20,'ACTIVOS CODIGO'!A:B,2,0) -> ACTIVO | C20: 1 | D20: =VLOOKUP(C20,'ACTIVOS CODIGO'!C:D,2,0) -> ACTIVO DEL TESORO = ACTIVO CORRIENTE | E20: 1 | F20: =VLOOKUP(E20,'ACTIVOS CODIGO'!E:F,2,0) -> ACTIVO DISPONIBLE | G20: 102 | H20: =VLOOKUP(G20,'PUB 21'!$A$1:$B$29,2,0) -> TESORERIA MUNICIPAL | I20: 1 | J20: BANCOS PUBLICOS Y PRIVADOS | K20: 1 | L20: BANCO PUBLICO | M20: =CONCATENATE(TEXT(A20,"0"),"-",TEXT(C20,"0"),"-",TEXT(E20,"0"),"-",TEXT(LEFT(G20,2),"00"),"-",TEXT(RIGHT(G20,1),"0"),TEXT(I20,"0"),"-",TEXT(K20,"00")) -> 1-1-1-10-21-01 | N20: =IF(L20="",IF(J20="",IF(H20="",IF(F20="",IF(D20="",B20,D20),F20),H20),J20),L20) -> BANCO PUBLICO | O20: =IF(P20="",0,IF(M19=M20,IF(O19="",0,O19)+1,"")) -> 11 | P20: I.M.C.P 0014103469 ING. EXT. 2021 | Q20: =CONCATENATE(TEXT(A20,"0"),"-",TEXT(C20,"0"),"-",TEXT(E20,"0"),"-",TEXT(LEFT(G20,2),"00"),"-",TEXT(RIGHT(G20,1),"0"),TEXT(I20,"0"),"-",TEXT(K20,"00"),"-",TEXT(O20,"000")) -> 1-1-1-10-21-01-011 | R20: =IF(P20="",IF(L20="",IF(J20="",IF(H20="",IF(F20="",IF(D20="",B20,D20),F20),H20),J20),L20),P20) -> I.M.C.P 0014103469 ING. EXT. 2021
A21: 1 | B21: =VLOOKUP(A21,'ACTIVOS CODIGO'!A:B,2,0) -> ACTIVO | C21: 1 | D21: =VLOOKUP(C21,'ACTIVOS CODIGO'!C:D,2,0) -> ACTIVO DEL TESORO = ACTIVO CORRIENTE | E21: 1 | F21: =VLOOKUP(E21,'ACTIVOS CODIGO'!E:F,2,0) -> ACTIVO DISPONIBLE | G21: 102 | H21: =VLOOKUP(G21,'PUB 21'!$A$1:$B$29,2,0) -> TESORERIA MUNICIPAL | I21: 1 | J21: BANCOS PUBLICOS Y PRIVADOS | K21: 1 | L21: BANCO PUBLICO | M21: =CONCATENATE(TEXT(A21,"0"),"-",TEXT(C21,"0"),"-",TEXT(E21,"0"),"-",TEXT(LEFT(G21,2),"00"),"-",TEXT(RIGHT(G21,1),"0"),TEXT(I21,"0"),"-",TEXT(K21,"00")) -> 1-1-1-10-21-01 | N21: =IF(L21="",IF(J21="",IF(H21="",IF(F21="",IF(D21="",B21,D21),F21),H21),J21),L21) -> BANCO PUBLICO | O21: =IF(P21="",0,IF(M20=M21,IF(O20="",0,O20)+1,"")) -> 12 | P21: I.M.C.P 0014106082 ING. NO TRIBUTARIOS 2021 | Q21: =CONCATENATE(TEXT(A21,"0"),"-",TEXT(C21,"0"),"-",TEXT(E21,"0"),"-",TEXT(LEFT(G21,2),"00"),"-",TEXT(RIGHT(G21,1),"0"),TEXT(I21,"0"),"-",TEXT(K21,"00"),"-",TEXT(O21,"000")) -> 1-1-1-10-21-01-012 | R21: =IF(P21="",IF(L21="",IF(J21="",IF(H21="",IF(F21="",IF(D21="",B21,D21),F21),H21),J21),L21),P21) -> I.M.C.P 0014106082 ING. NO TRIBUTARIOS 2021
... A49: 1 | B49: =VLOOKUP(A49,'ACTIVOS CODIGO'!A:B,2,0) -> ACTIVO | C49: 1 | D49: =VLOOKUP(C49,'ACTIVOS CODIGO'!C:D,2,0) -> ACTIVO DEL TESORO = ACTIVO CORRIENTE | E49: 1 | F49: =VLOOKUP(E49,'ACTIVOS CODIGO'!E:F,2,0) -> ACTIVO DISPONIBLE | G49: 102 | H49: =VLOOKUP(G49,'PUB 21'!$A$1:$B$29,2,0) -> TESORERIA MUNICIPAL | I49: 1 | J49: BANCOS PUBLICOS Y PRIVADOS | K49: 1 | L49: BANCO PUBLICO | M49: =CONCATENATE(TEXT(A49,"0"),"-",TEXT(C49,"0"),"-",TEXT(E49,"0"),"-",TEXT(LEFT(G49,2),"00"),"-",TEXT(RIGHT(G49,1),"0"),TEXT(I49,"0"),"-",TEXT(K49,"00")) -> 1-1-1-10-21-01 | N49: =IF(L49="",IF(J49="",IF(H49="",IF(F49="",IF(D49="",B49,D49),F49),H49),J49),L49) -> BANCO PUBLICO | O49: =IF(P49="",0,IF(M48=M49,IF(O48="",0,O48)+1,"")) -> 40 | P49: PARTIDA POR CERTIFICAR VENEZUELA | Q49: =CONCATENATE(TEXT(A49,"0"),"-",TEXT(C49,"0"),"-",TEXT(E49,"0"),"-",TEXT(LEFT(G49,2),"00"),"-",TEXT(RIGHT(G49,1),"0"),TEXT(I49,"0"),"-",TEXT(K49,"00"),"-",TEXT(O49,"000")) -> 1-1-1-10-21-01-040 | R49: =IF(P49="",IF(L49="",IF(J49="",IF(H49="",IF(F49="",IF(D49="",B49,D49),F49),H49),J49),L49),P49) -> PARTIDA POR CERTIFICAR VENEZUELA
A50: 1 | B50: =VLOOKUP(A50,'ACTIVOS CODIGO'!A:B,2,0) -> ACTIVO | C50: 1 | D50: =VLOOKUP(C50,'ACTIVOS CODIGO'!C:D,2,0) -> ACTIVO DEL TESORO = ACTIVO CORRIENTE | E50: 1 | F50: =VLOOKUP(E50,'ACTIVOS CODIGO'!E:F,2,0) -> ACTIVO DISPONIBLE | G50: 102 | H50: =VLOOKUP(G50,'PUB 21'!$A$1:$B$29,2,0) -> TESORERIA MUNICIPAL | I50: 1 | J50: BANCOS PUBLICOS Y PRIVADOS | K50: 2 | L50: BANCO PRIVADO | M50: =CONCATENATE(TEXT(A50,"0"),"-",TEXT(C50,"0"),"-",TEXT(E50,"0"),"-",TEXT(LEFT(G50,2),"00"),"-",TEXT(RIGHT(G50,1),"0"),TEXT(I50,"0"),"-",TEXT(K50,"00")) -> 1-1-1-10-21-02 | N50: =IF(L50="",IF(J50="",IF(H50="",IF(F50="",IF(D50="",B50,D50),F50),H50),J50),L50) -> BANCO PRIVADO | O50: =IF(P50="",0,IF(M49=M50,IF(O49="",0,O49)+1,"")) -> 0 | Q50: =CONCATENATE(TEXT(A50,"0"),"-",TEXT(C50,"0"),"-",TEXT(E50,"0"),"-",TEXT(LEFT(G50,2),"00"),"-",TEXT(RIGHT(G50,1),"0"),TEXT(I50,"0"),"-",TEXT(K50,"00"),"-",TEXT(O50,"000")) -> 1-1-1-10-21-02-000 | R50: =IF(P50="",IF(L50="",IF(J50="",IF(H50="",IF(F50="",IF(D50="",B50,D50),F50),H50),J50),L50),P50) -> BANCO PRIVADO
A51: 1 | B51: =VLOOKUP(A51,'ACTIVOS CODIGO'!A:B,2,0) -> ACTIVO | C51: 1 | D51: =VLOOKUP(C51,'ACTIVOS CODIGO'!C:D,2,0) -> ACTIVO DEL TESORO = ACTIVO CORRIENTE | E51: 1 | F51: =VLOOKUP(E51,'ACTIVOS CODIGO'!E:F,2,0) -> ACTIVO DISPONIBLE | G51: 102 | H51: =VLOOKUP(G51,'PUB 21'!$A$1:$B$29,2,0) -> TESORERIA MUNICIPAL | I51: 1 | J51: BANCOS PUBLICOS Y PRIVADOS | K51: 2 | L51: BANCO PRIVADO | M51: =CONCATENATE(TEXT(A51,"0"),"-",TEXT(C51,"0"),"-",TEXT(E51,"0"),"-",TEXT(LEFT(G51,2),"00"),"-",TEXT(RIGHT(G51,1),"0"),TEXT(I51,"0"),"-",TEXT(K51,"00")) -> 1-1-1-10-21-02 | N51: =IF(L51="",IF(J51="",IF(H51="",IF(F51="",IF(D51="",B51,D51),F51),H51),J51),L51) -> BANCO PRIVADO | O51: =IF(P51="",0,IF(M50=M51,IF(O50="",0,O50)+1,"")) -> 1 | P51: BANESCO 0134-0031-89-0311159052 | Q51: =CONCATENATE(TEXT(A51,"0"),"-",TEXT(C51,"0"),"-",TEXT(E51,"0"),"-",TEXT(LEFT(G51,2),"00"),"-",TEXT(RIGHT(G51,1),"0"),TEXT(I51,"0"),"-",TEXT(K51,"00"),"-",TEXT(O51,"000")) -> 1-1-1-10-21-02-001 | R51: =IF(P51="",IF(L51="",IF(J51="",IF(H51="",IF(F51="",IF(D51="",B51,D51),F51),H51),J51),L51),P51) -> BANESCO 0134-0031-89-0311159052
A52: 1 | B52: =VLOOKUP(A52,'ACTIVOS CODIGO'!A:B,2,0) -> ACTIVO | C52: 1 | D52: =VLOOKUP(C52,'ACTIVOS CODIGO'!C:D,2,0) -> ACTIVO DEL TESORO = ACTIVO CORRIENTE | E52: 1 | F52: =VLOOKUP(E52,'ACTIVOS CODIGO'!E:F,2,0) -> ACTIVO DISPONIBLE | G52: 102 | H52: =VLOOKUP(G52,'PUB 21'!$A$1:$B$29,2,0) -> TESORERIA MUNICIPAL | I52: 1 | J52: BANCOS PUBLICOS Y PRIVADOS | K52: 2 | L52: BANCO PRIVADO | M52: =CONCATENATE(TEXT(A52,"0"),"-",TEXT(C52,"0"),"-",TEXT(E52,"0"),"-",TEXT(LEFT(G52,2),"00"),"-",TEXT(RIGHT(G52,1),"0"),TEXT(I52,"0"),"-",TEXT(K52,"00")) -> 1-1-1-10-21-02 | N52: =IF(L52="",IF(J52="",IF(H52="",IF(F52="",IF(D52="",B52,D52),F52),H52),J52),L52) -> BANCO PRIVADO | O52: =IF(P52="",0,IF(M51=M52,IF(O51="",0,O51)+1,"")) -> 2 | P52: B.O.D. 0116-0032-85-0028290615 | Q52: =CONCATENATE(TEXT(A52,"0"),"-",TEXT(C52,"0"),"-",TEXT(E52,"0"),"-",TEXT(LEFT(G52,2),"00"),"-",TEXT(RIGHT(G52,1),"0"),TEXT(I52,"0"),"-",TEXT(K52,"00"),"-",TEXT(O52,"000")) -> 1-1-1-10-21-02-002 | R52: =IF(P52="",IF(L52="",IF(J52="",IF(H52="",IF(F52="",IF(D52="",B52,D52),F52),H52),J52),L52),P52) -> B.O.D. 0116-0032-85-0028290615
A53: 1 | B53: =VLOOKUP(A53,'ACTIVOS CODIGO'!A:B,2,0) -> ACTIVO | C53: 1 | D53: =VLOOKUP(C53,'ACTIVOS CODIGO'!C:D,2,0) -> ACTIVO DEL TESORO = ACTIVO CORRIENTE | E53: 1 | F53: =VLOOKUP(E53,'ACTIVOS CODIGO'!E:F,2,0) -> ACTIVO DISPONIBLE | G53: 102 | H53: =VLOOKUP(G53,'PUB 21'!$A$1:$B$29,2,0) -> TESORERIA MUNICIPAL | I53: 1 | J53: BANCOS PUBLICOS Y PRIVADOS | K53: 2 | L53: BANCO PRIVADO | M53: =CONCATENATE(TEXT(A53,"0"),"-",TEXT(C53,"0"),"-",TEXT(E53,"0"),"-",TEXT(LEFT(G53,2),"00"),"-",TEXT(RIGHT(G53,1),"0"),TEXT(I53,"0"),"-",TEXT(K53,"00")) -> 1-1-1-10-21-02 | N53: =IF(L53="",IF(J53="",IF(H53="",IF(F53="",IF(D53="",B53,D53),F53),H53),J53),L53) -> BANCO PRIVADO | O53: =IF(P53="",0,IF(M52=M53,IF(O52="",0,O52)+1,"")) -> 3 | P53: PROVINCIAL 0108-0582-21-9010005000 | Q53: =CONCATENATE(TEXT(A53,"0"),"-",TEXT(C53,"0"),"-",TEXT(E53,"0"),"-",TEXT(LEFT(G53,2),"00"),"-",TEXT(RIGHT(G53,1),"0"),TEXT(I53,"0"),"-",TEXT(K53,"00"),"-",TEXT(O53,"000")) -> 1-1-1-10-21-02-003 | R53: =IF(P53="",IF(L53="",IF(J53="",IF(H53="",IF(F53="",IF(D53="",B53,D53),F53),H53),J53),L53),P53) -> PROVINCIAL 0108-0582-21-9010005000
A54: 1 | B54: =VLOOKUP(A54,'ACTIVOS CODIGO'!A:B,2,0) -> ACTIVO | C54: 1 | D54: =VLOOKUP(C54,'ACTIVOS CODIGO'!C:D,2,0) -> ACTIVO DEL TESORO = ACTIVO CORRIENTE | E54: 1 | F54: =VLOOKUP(E54,'ACTIVOS CODIGO'!E:F,2,0) -> ACTIVO DISPONIBLE | G54: 102 | H54: =VLOOKUP(G54,'PUB 21'!$A$1:$B$29,2,0) -> TESORERIA MUNICIPAL | I54: 1 | J54: BANCOS PUBLICOS Y PRIVADOS | K54: 2 | L54: BANCO PRIVADO | M54: =CONCATENATE(TEXT(A54,"0"),"-",TEXT(C54,"0"),"-",TEXT(E54,"0"),"-",TEXT(LEFT(G54,2),"00"),"-",TEXT(RIGHT(G54,1),"0"),TEXT(I54,"0"),"-",TEXT(K54,"00")) -> 1-1-1-10-21-02 | N54: =IF(L54="",IF(J54="",IF(H54="",IF(F54="",IF(D54="",B54,D54),F54),H54),J54),L54) -> BANCO PRIVADO | O54: =IF(P54="",0,IF(M53=M54,IF(O53="",0,O53)+1,"")) -> 4 | P54: FONDO COMUN 0151-0100-85-3000872449 | Q54: =CONCATENATE(TEXT(A54,"0"),"-",TEXT(C54,"0"),"-",TEXT(E54,"0"),"-",TEXT(LEFT(G54,2),"00"),"-",TEXT(RIGHT(G54,1),"0"),TEXT(I54,"0"),"-",TEXT(K54,"00"),"-",TEXT(O54,"000")) -> 1-1-1-10-21-02-004 | R54: =IF(P54="",IF(L54="",IF(J54="",IF(H54="",IF(F54="",IF(D54="",B54,D54),F54),H54),J54),L54),P54) -> FONDO COMUN 0151-0100-85-3000872449
A55: 1 | B55: =VLOOKUP(A55,'ACTIVOS CODIGO'!A:B,2,0) -> ACTIVO | C55: 1 | D55: =VLOOKUP(C55,'ACTIVOS CODIGO'!C:D,2,0) -> ACTIVO DEL TESORO = ACTIVO CORRIENTE | E55: 1 | F55: =VLOOKUP(E55,'ACTIVOS CODIGO'!E:F,2,0) -> ACTIVO DISPONIBLE | G55: 102 | H55: =VLOOKUP(G55,'PUB 21'!$A$1:$B$29,2,0) -> TESORERIA MUNICIPAL | I55: 1 | J55: BANCOS PUBLICOS Y PRIVADOS | K55: 2 | L55: BANCO PRIVADO | M55: =CONCATENATE(TEXT(A55,"0"),"-",TEXT(C55,"0"),"-",TEXT(E55,"0"),"-",TEXT(LEFT(G55,2),"00"),"-",TEXT(RIGHT(G55,1),"0"),TEXT(I55,"0"),"-",TEXT(K55,"00")) -> 1-1-1-10-21-02 | N55: =IF(L55="",IF(J55="",IF(H55="",IF(F55="",IF(D55="",B55,D55),F55),H55),J55),L55) -> BANCO PRIVADO | O55: =IF(P55="",0,IF(M54=M55,IF(O54="",0,O54)+1,"")) -> 5 | P55: 0102-0762-210000050322 | Q55: =CONCATENATE(TEXT(A55,"0"),"-",TEXT(C55,"0"),"-",TEXT(E55,"0"),"-",TEXT(LEFT(G55,2),"00"),"-",TEXT(RIGHT(G55,1),"0"),TEXT(I55,"0"),"-",TEXT(K55,"00"),"-",TEXT(O55,"000")) -> 1-1-1-10-21-02-005 | R55: =IF(P55="",IF(L55="",IF(J55="",IF(H55="",IF(F55="",IF(D55="",B55,D55),F55),H55),J55),L55),P55) -> 0102-0762-210000050322
A56: 1 | B56: =VLOOKUP(A56,'ACTIVOS CODIGO'!A:B,2,0) -> ACTIVO | C56: 1 | D56: =VLOOKUP(C56,'ACTIVOS CODIGO'!C:D,2,0) -> ACTIVO DEL TESORO = ACTIVO CORRIENTE | E56: 1 | F56: =VLOOKUP(E56,'ACTIVOS CODIGO'!E:F,2,0) -> ACTIVO DISPONIBLE | G56: 102 | H56: =VLOOKUP(G56,'PUB 21'!$A$1:$B$29,2,0) -> TESORERIA MUNICIPAL | I56: 1 | J56: BANCOS PUBLICOS Y PRIVADOS | K56: 2 | L56: BANCO PRIVADO | M56: =CONCATENATE(TEXT(A56,"0"),"-",TEXT(C56,"0"),"-",TEXT(E56,"0"),"-",TEXT(LEFT(G56,2),"00"),"-",TEXT(RIGHT(G56,1),"0"),TEXT(I56,"0"),"-",TEXT(K56,"00")) -> 1-1-1-10-21-02 | N56: =IF(L56="",IF(J56="",IF(H56="",IF(F56="",IF(D56="",B56,D56),F56),H56),J56),L56) -> BANCO PRIVADO | O56: =IF(P56="",0,IF(M55=M56,IF(O55="",0,O55)+1,"")) -> 6 | P56: I.M.C.P 0601-0001-21-0014098545 | Q56: =CONCATENATE(TEXT(A56,"0"),"-",TEXT(C56,"0"),"-",TEXT(E56,"0"),"-",TEXT(LEFT(G56,2),"00"),"-",TEXT(RIGHT(G56,1),"0"),TEXT(I56,"0"),"-",TEXT(K56,"00"),"-",TEXT(O56,"000")) -> 1-1-1-10-21-02-006 | R56: =IF(P56="",IF(L56="",IF(J56="",IF(H56="",IF(F56="",IF(D56="",B56,D56),F56),H56),J56),L56),P56) -> I.M.C.P 0601-0001-21-0014098545
A57: 1 | B57: =VLOOKUP(A57,'ACTIVOS CODIGO'!A:B,2,0) -> ACTIVO | C57: 1 | D57: =VLOOKUP(C57,'ACTIVOS CODIGO'!C:D,2,0) -> ACTIVO DEL TESORO = ACTIVO CORRIENTE | E57: 1 | F57: =VLOOKUP(E57,'ACTIVOS CODIGO'!E:F,2,0) -> ACTIVO DISPONIBLE | G57: 102 | H57: =VLOOKUP(G57,'PUB 21'!$A$1:$B$29,2,0) -> TESORERIA MUNICIPAL | I57: 1 | J57: BANCOS PUBLICOS Y PRIVADOS | K57: 2 | L57: BANCO PRIVADO | M57: =CONCATENATE(TEXT(A57,"0"),"-",TEXT(C57,"0"),"-",TEXT(E57,"0"),"-",TEXT(LEFT(G57,2),"00"),"-",TEXT(RIGHT(G57,1),"0"),TEXT(I57,"0"),"-",TEXT(K57,"00")) -> 1-1-1-10-21-02 | N57: =IF(L57="",IF(J57="",IF(H57="",IF(F57="",IF(D57="",B57,D57),F57),H57),J57),L57) -> BANCO PRIVADO | O57: =IF(P57="",0,IF(M56=M57,IF(O56="",0,O56)+1,"")) -> 7 | P57: BNC 01168884 | Q57: =CONCATENATE(TEXT(A57,"0"),"-",TEXT(C57,"0"),"-",TEXT(E57,"0"),"-",TEXT(LEFT(G57,2),"00"),"-",TEXT(RIGHT(G57,1),"0"),TEXT(I57,"0"),"-",TEXT(K57,"00"),"-",TEXT(O57,"000")) -> 1-1-1-10-21-02-007 | R57: =IF(P57="",IF(L57="",IF(J57="",IF(H57="",IF(F57="",IF(D57="",B57,D57),F57),H57),J57),L57),P57) -> BNC 01168884
A58: 1 | B58: =VLOOKUP(A58,'ACTIVOS CODIGO'!A:B,2,0) -> ACTIVO | C58: 1 | D58: =VLOOKUP(C58,'ACTIVOS CODIGO'!C:D,2,0) -> ACTIVO DEL TESORO = ACTIVO CORRIENTE | E58: 1 | F58: =VLOOKUP(E58,'ACTIVOS CODIGO'!E:F,2,0) -> ACTIVO DISPONIBLE | G58: 102 | H58: =VLOOKUP(G58,'PUB 21'!$A$1:$B$29,2,0) -> TESORERIA MUNICIPAL | I58: 1 | J58: BANCOS PUBLICOS Y PRIVADOS | K58: 2 | L58: BANCO PRIVADO | M58: =CONCATENATE(TEXT(A58,"0"),"-",TEXT(C58,"0"),"-",TEXT(E58,"0"),"-",TEXT(LEFT(G58,2),"00"),"-",TEXT(RIGHT(G58,1),"0"),TEXT(I58,"0"),"-",TEXT(K58,"00")) -> 1-1-1-10-21-02 | N58: =IF(L58="",IF(J58="",IF(H58="",IF(F58="",IF(D58="",B58,D58),F58),H58),J58),L58) -> BANCO PRIVADO | O58: =IF(P58="",0,IF(M57=M58,IF(O57="",0,O57)+1,"")) -> 8 | P58: BANCARIBE 0114015977 1590175737 | Q58: =CONCATENATE(TEXT(A58,"0"),"-",TEXT(C58,"0"),"-",TEXT(E58,"0"),"-",TEXT(LEFT(G58,2),"00"),"-",TEXT(RIGHT(G58,1),"0"),TEXT(I58,"0"),"-",TEXT(K58,"00"),"-",TEXT(O58,"000")) -> 1-1-1-10-21-02-008 | R58: =IF(P58="",IF(L58="",IF(J58="",IF(H58="",IF(F58="",IF(D58="",B58,D58),F58),H58),J58),L58),P58) -> BANCARIBE 0114015977 1590175737
A59: 1 | B59: =VLOOKUP(A59,'ACTIVOS CODIGO'!A:B,2,0) -> ACTIVO | C59: 1 | D59: =VLOOKUP(C59,'ACTIVOS CODIGO'!C:D,2,0) -> ACTIVO DEL TESORO = ACTIVO CORRIENTE | E59: 1 | F59: =VLOOKUP(E59,'ACTIVOS CODIGO'!E:F,2,0) -> ACTIVO DISPONIBLE | G59: 102 | H59: =VLOOKUP(G59,'PUB 21'!$A$1:$B$29,2,0) -> TESORERIA MUNICIPAL | I59: 1 | J59: BANCOS PUBLICOS Y PRIVADOS | K59: 2 | L59: BANCO PRIVADO | M59: =CONCATENATE(TEXT(A59,"0"),"-",TEXT(C59,"0"),"-",TEXT(E59,"0"),"-",TEXT(LEFT(G59,2),"00"),"-",TEXT(RIGHT(G59,1),"0"),TEXT(I59,"0"),"-",TEXT(K59,"00")) -> 1-1-1-10-21-02 | N59: =IF(L59="",IF(J59="",IF(H59="",IF(F59="",IF(D59="",B59,D59),F59),H59),J59),L59) -> BANCO PRIVADO | O59: =IF(P59="",0,IF(M58=M59,IF(O58="",0,O58)+1,"")) -> 9 | P59: FONDO COMUN 300077149 | Q59: =CONCATENATE(TEXT(A59,"0"),"-",TEXT(C59,"0"),"-",TEXT(E59,"0"),"-",TEXT(LEFT(G59,2),"00"),"-",TEXT(RIGHT(G59,1),"0"),TEXT(I59,"0"),"-",TEXT(K59,"00"),"-",TEXT(O59,"000")) -> 1-1-1-10-21-02-009 | R59: =IF(P59="",IF(L59="",IF(J59="",IF(H59="",IF(F59="",IF(D59="",B59,D59),F59),H59),J59),L59),P59) -> FONDO COMUN 300077149
A60: 1 | B60: =VLOOKUP(A60,'ACTIVOS CODIGO'!A:B,2,0) -> ACTIVO | C60: 1 | D60: =VLOOKUP(C60,'ACTIVOS CODIGO'!C:D,2,0) -> ACTIVO DEL TESORO = ACTIVO CORRIENTE | E60: 1 | F60: =VLOOKUP(E60,'ACTIVOS CODIGO'!E:F,2,0) -> ACTIVO DISPONIBLE | G60: 102 | H60: =VLOOKUP(G60,'PUB 21'!$A$1:$B$29,2,0) -> TESORERIA MUNICIPAL | I60: 1 | J60: BANCOS PUBLICOS Y PRIVADOS | K60: 2 | L60: BANCO PRIVADO | M60: =CONCATENATE(TEXT(A60,"0"),"-",TEXT(C60,"0"),"-",TEXT(E60,"0"),"-",TEXT(LEFT(G60,2),"00"),"-",TEXT(RIGHT(G60,1),"0"),TEXT(I60,"0"),"-",TEXT(K60,"00")) -> 1-1-1-10-21-02 | N60: =IF(L60="",IF(J60="",IF(H60="",IF(F60="",IF(D60="",B60,D60),F60),H60),J60),L60) -> BANCO PRIVADO | O60: =IF(P60="",0,IF(M59=M60,IF(O59="",0,O59)+1,"")) -> 10 | P60: BANESCO CUENTA CORRIENTE 4782 | Q60: =CONCATENATE(TEXT(A60,"0"),"-",TEXT(C60,"0"),"-",TEXT(E60,"0"),"-",TEXT(LEFT(G60,2),"00"),"-",TEXT(RIGHT(G60,1),"0"),TEXT(I60,"0"),"-",TEXT(K60,"00"),"-",TEXT(O60,"000")) -> 1-1-1-10-21-02-010 | R60: =IF(P60="",IF(L60="",IF(J60="",IF(H60="",IF(F60="",IF(D60="",B60,D60),F60),H60),J60),L60),P60) -> BANESCO CUENTA CORRIENTE 4782
A61: 1 | B61: =VLOOKUP(A61,'ACTIVOS CODIGO'!A:B,2,0) -> ACTIVO | C61: 1 | D61: =VLOOKUP(C61,'ACTIVOS CODIGO'!C:D,2,0) -> ACTIVO DEL TESORO = ACTIVO CORRIENTE | E61: 1 | F61: =VLOOKUP(E61,'ACTIVOS CODIGO'!E:F,2,0) -> ACTIVO DISPONIBLE | G61: 102 | H61: =VLOOKUP(G61,'PUB 21'!$A$1:$B$29,2,0) -> TESORERIA MUNICIPAL | I61: 1 | J61: BANCOS PUBLICOS Y PRIVADOS | K61: 2 | L61: BANCO PRIVADO | M61: =CONCATENATE(TEXT(A61,"0"),"-",TEXT(C61,"0"),"-",TEXT(E61,"0"),"-",TEXT(LEFT(G61,2),"00"),"-",TEXT(RIGHT(G61,1),"0"),TEXT(I61,"0"),"-",TEXT(K61,"00")) -> 1-1-1-10-21-02 | N61: =IF(L61="",IF(J61="",IF(H61="",IF(F61="",IF(D61="",B61,D61),F61),H61),J61),L61) -> BANCO PRIVADO | O61: =IF(P61="",0,IF(M60=M61,IF(O60="",0,O60)+1,"")) -> 11 | P61: BANCARIBE 0114-0159-76-1590175990 CTA. GASTOS 2021 | Q61: =CONCATENATE(TEXT(A61,"0"),"-",TEXT(C61,"0"),"-",TEXT(E61,"0"),"-",TEXT(LEFT(G61,2),"00"),"-",TEXT(RIGHT(G61,1),"0"),TEXT(I61,"0"),"-",TEXT(K61,"00"),"-",TEXT(O61,"000")) -> 1-1-1-10-21-02-011 | R61: =IF(P61="",IF(L61="",IF(J61="",IF(H61="",IF(F61="",IF(D61="",B61,D61),F61),H61),J61),L61),P61) -> BANCARIBE 0114-0159-76-1590175990 CTA. GASTOS 2021
A62: 1 | B62: =VLOOKUP(A62,'ACTIVOS CODIGO'!A:B,2,0) -> ACTIVO | C62: 1 | D62: =VLOOKUP(C62,'ACTIVOS CODIGO'!C:D,2,0) -> ACTIVO DEL TESORO = ACTIVO CORRIENTE | E62: 1 | F62: =VLOOKUP(E62,'ACTIVOS CODIGO'!E:F,2,0) -> ACTIVO DISPONIBLE | G62: 102 | H62: =VLOOKUP(G62,'PUB 21'!$A$1:$B$29,2,0) -> TESORERIA MUNICIPAL | I62: 1 | J62: BANCOS PUBLICOS Y PRIVADOS | K62: 2 | L62: BANCO PRIVADO | M62: =CONCATENATE(TEXT(A62,"0"),"-",TEXT(C62,"0"),"-",TEXT(E62,"0"),"-",TEXT(LEFT(G62,2),"00"),"-",TEXT(RIGHT(G62,1),"0"),TEXT(I62,"0"),"-",TEXT(K62,"00")) -> 1-1-1-10-21-02 | N62: =IF(L62="",IF(J62="",IF(H62="",IF(F62="",IF(D62="",B62,D62),F62),H62),J62),L62) -> BANCO PRIVADO | O62: =IF(P62="",0,IF(M61=M62,IF(O61="",0,O61)+1,"")) -> 12 | P62: BANCARIBE 1590176008 FISCO MUNICIPAL 2021 | Q62: =CONCATENATE(TEXT(A62,"0"),"-",TEXT(C62,"0"),"-",TEXT(E62,"0"),"-",TEXT(LEFT(G62,2),"00"),"-",TEXT(RIGHT(G62,1),"0"),TEXT(I62,"0"),"-",TEXT(K62,"00"),"-",TEXT(O62,"000")) -> 1-1-1-10-21-02-012 | R62: =IF(P62="",IF(L62="",IF(J62="",IF(H62="",IF(F62="",IF(D62="",B62,D62),F62),H62),J62),L62),P62) -> BANCARIBE 1590176008 FISCO MUNICIPAL 2021
... A76: 1 | B76: =VLOOKUP(A76,'ACTIVOS CODIGO'!A:B,2,0) -> ACTIVO | C76: 1 | D76: =VLOOKUP(C76,'ACTIVOS CODIGO'!C:D,2,0) -> ACTIVO DEL TESORO = ACTIVO CORRIENTE | E76: 1 | F76: =VLOOKUP(E76,'ACTIVOS CODIGO'!E:F,2,0) -> ACTIVO DISPONIBLE | G76: 102 | H76: =VLOOKUP(G76,'PUB 21'!$A$1:$B$29,2,0) -> TESORERIA MUNICIPAL | I76: 1 | J76: BANCOS PUBLICOS Y PRIVADOS | K76: 2 | L76: BANCO PRIVADO | M76: =CONCATENATE(TEXT(A76,"0"),"-",TEXT(C76,"0"),"-",TEXT(E76,"0"),"-",TEXT(LEFT(G76,2),"00"),"-",TEXT(RIGHT(G76,1),"0"),TEXT(I76,"0"),"-",TEXT(K76,"00")) -> 1-1-1-10-21-02 | N76: =IF(L76="",IF(J76="",IF(H76="",IF(F76="",IF(D76="",B76,D76),F76),H76),J76),L76) -> BANCO PRIVADO | O76: =IF(P76="",0,IF(M75=M76,IF(O75="",0,O75)+1,"")) -> 26 | P76: PARTIDA POR CERTIFICAR BANESCO | Q76: =CONCATENATE(TEXT(A76,"0"),"-",TEXT(C76,"0"),"-",TEXT(E76,"0"),"-",TEXT(LEFT(G76,2),"00"),"-",TEXT(RIGHT(G76,1),"0"),TEXT(I76,"0"),"-",TEXT(K76,"00"),"-",TEXT(O76,"000")) -> 1-1-1-10-21-02-026 | R76: =IF(P76="",IF(L76="",IF(J76="",IF(H76="",IF(F76="",IF(D76="",B76,D76),F76),H76),J76),L76),P76) -> PARTIDA POR CERTIFICAR BANESCO
A77: 1 | B77: =VLOOKUP(A77,'ACTIVOS CODIGO'!A:B,2,0) -> ACTIVO | C77: 1 | D77: =VLOOKUP(C77,'ACTIVOS CODIGO'!C:D,2,0) -> ACTIVO DEL TESORO = ACTIVO CORRIENTE | E77: 1 | F77: =VLOOKUP(E77,'ACTIVOS CODIGO'!E:F,2,0) -> ACTIVO DISPONIBLE | G77: 110 | H77: =VLOOKUP(G77,'PUB 21'!$A$1:$B$29,2,0) -> FONDOS DEL SITUADO COORDINADO | M77: =CONCATENATE(TEXT(A77,"0"),"-",TEXT(C77,"0"),"-",TEXT(E77,"0"),"-",TEXT(LEFT(G77,2),"00"),"-",TEXT(RIGHT(G77,1),"0"),TEXT(I77,"0"),"-",TEXT(K77,"00")) -> 1-1-1-11-00-00 | N77: =IF(L77="",IF(J77="",IF(H77="",IF(F77="",IF(D77="",B77,D77),F77),H77),J77),L77) -> FONDOS DEL SITUADO COORDINADO | O77: =IF(P77="",0,IF(M76=M77,IF(O76="",0,O76)+1,"")) -> 0 | Q77: =CONCATENATE(TEXT(A77,"0"),"-",TEXT(C77,"0"),"-",TEXT(E77,"0"),"-",TEXT(LEFT(G77,2),"00"),"-",TEXT(RIGHT(G77,1),"0"),TEXT(I77,"0"),"-",TEXT(K77,"00"),"-",TEXT(O77,"000")) -> 1-1-1-11-00-00-000 | R77: =IF(P77="",IF(L77="",IF(J77="",IF(H77="",IF(F77="",IF(D77="",B77,D77),F77),H77),J77),L77),P77) -> FONDOS DEL SITUADO COORDINADO
A78: 1 | B78: =VLOOKUP(A78,'ACTIVOS CODIGO'!A:B,2,0) -> ACTIVO | C78: 1 | D78: =VLOOKUP(C78,'ACTIVOS CODIGO'!C:D,2,0) -> ACTIVO DEL TESORO = ACTIVO CORRIENTE | E78: 1 | F78: =VLOOKUP(E78,'ACTIVOS CODIGO'!E:F,2,0) -> ACTIVO DISPONIBLE | G78: 110 | H78: =VLOOKUP(G78,'PUB 21'!$A$1:$B$29,2,0) -> FONDOS DEL SITUADO COORDINADO | M78: =CONCATENATE(TEXT(A78,"0"),"-",TEXT(C78,"0"),"-",TEXT(E78,"0"),"-",TEXT(LEFT(G78,2),"00"),"-",TEXT(RIGHT(G78,1),"0"),TEXT(I78,"0"),"-",TEXT(K78,"00")) -> 1-1-1-11-00-00 | N78: =IF(L78="",IF(J78="",IF(H78="",IF(F78="",IF(D78="",B78,D78),F78),H78),J78),L78) -> FONDOS DEL SITUADO COORDINADO | O78: =IF(P78="",0,IF(M77=M78,IF(O77="",0,O77)+1,"")) -> 1 | P78: I.M.C.P. 0601-0001-27-0014072037 | Q78: =CONCATENATE(TEXT(A78,"0"),"-",TEXT(C78,"0"),"-",TEXT(E78,"0"),"-",TEXT(LEFT(G78,2),"00"),"-",TEXT(RIGHT(G78,1),"0"),TEXT(I78,"0"),"-",TEXT(K78,"00"),"-",TEXT(O78,"000")) -> 1-1-1-11-00-00-001 | R78: =IF(P78="",IF(L78="",IF(J78="",IF(H78="",IF(F78="",IF(D78="",B78,D78),F78),H78),J78),L78),P78) -> I.M.C.P. 0601-0001-27-0014072037
A79: 1 | B79: =VLOOKUP(A79,'ACTIVOS CODIGO'!A:B,2,0) -> ACTIVO | C79: 1 | D79: =VLOOKUP(C79,'ACTIVOS CODIGO'!C:D,2,0) -> ACTIVO DEL TESORO = ACTIVO CORRIENTE | E79: 1 | F79: =VLOOKUP(E79,'ACTIVOS CODIGO'!E:F,2,0) -> ACTIVO DISPONIBLE | G79: 110 | H79: =VLOOKUP(G79,'PUB 21'!$A$1:$B$29,2,0) -> FONDOS DEL SITUADO COORDINADO | M79: =CONCATENATE(TEXT(A79,"0"),"-",TEXT(C79,"0"),"-",TEXT(E79,"0"),"-",TEXT(LEFT(G79,2),"00"),"-",TEXT(RIGHT(G79,1),"0"),TEXT(I79,"0"),"-",TEXT(K79,"00")) -> 1-1-1-11-00-00 | N79: =IF(L79="",IF(J79="",IF(H79="",IF(F79="",IF(D79="",B79,D79),F79),H79),J79),L79) -> FONDOS DEL SITUADO COORDINADO | O79: =IF(P79="",0,IF(M78=M79,IF(O78="",0,O78)+1,"")) -> 2 | P79: I.M.C.P. 004103477 SITUADO MUNICIPAL 2021 | Q79: =CONCATENATE(TEXT(A79,"0"),"-",TEXT(C79,"0"),"-",TEXT(E79,"0"),"-",TEXT(LEFT(G79,2),"00"),"-",TEXT(RIGHT(G79,1),"0"),TEXT(I79,"0"),"-",TEXT(K79,"00"),"-",TEXT(O79,"000")) -> 1-1-1-11-00-00-002 | R79: =IF(P79="",IF(L79="",IF(J79="",IF(H79="",IF(F79="",IF(D79="",B79,D79),F79),H79),J79),L79),P79) -> I.M.C.P. 004103477 SITUADO MUNICIPAL 2021
A80: 1 | B80: =VLOOKUP(A80,'ACTIVOS CODIGO'!A:B,2,0) -> ACTIVO | C80: 1 | D80: =VLOOKUP(C80,'ACTIVOS CODIGO'!C:D,2,0) -> ACTIVO DEL TESORO = ACTIVO CORRIENTE | E80: 1 | F80: =VLOOKUP(E80,'ACTIVOS CODIGO'!E:F,2,0) -> ACTIVO DISPONIBLE | G80: 110 | H80: =VLOOKUP(G80,'PUB 21'!$A$1:$B$29,2,0) -> FONDOS DEL SITUADO COORDINADO | M80: =CONCATENATE(TEXT(A80,"0"),"-",TEXT(C80,"0"),"-",TEXT(E80,"0"),"-",TEXT(LEFT(G80,2),"00"),"-",TEXT(RIGHT(G80,1),"0"),TEXT(I80,"0"),"-",TEXT(K80,"00")) -> 1-1-1-11-00-00 | N80: =IF(L80="",IF(J80="",IF(H80="",IF(F80="",IF(D80="",B80,D80),F80),H80),J80),L80) -> FONDOS DEL SITUADO COORDINADO | O80: =IF(P80="",0,IF(M79=M80,IF(O79="",0,O79)+1,"")) -> 3 | P80: I.M.C.P. 0601-0001-21-0014107205 "A.M.L. SITUADO MCPAL. 2022" | Q80: =CONCATENATE(TEXT(A80,"0"),"-",TEXT(C80,"0"),"-",TEXT(E80,"0"),"-",TEXT(LEFT(G80,2),"00"),"-",TEXT(RIGHT(G80,1),"0"),TEXT(I80,"0"),"-",TEXT(K80,"00"),"-",TEXT(O80,"000")) -> 1-1-1-11-00-00-003 | R80: =IF(P80="",IF(L80="",IF(J80="",IF(H80="",IF(F80="",IF(D80="",B80,D80),F80),H80),J80),L80),P80) -> I.M.C.P. 0601-0001-21-0014107205 "A.M.L. SITUADO MCPAL. 2022"
A81: 1 | B81: =VLOOKUP(A81,'ACTIVOS CODIGO'!A:B,2,0) -> ACTIVO | C81: 1 | D81: =VLOOKUP(C81,'ACTIVOS CODIGO'!C:D,2,0) -> ACTIVO DEL TESORO = ACTIVO CORRIENTE | E81: 1 | F81: =VLOOKUP(E81,'ACTIVOS CODIGO'!E:F,2,0) -> ACTIVO DISPONIBLE | G81: 110 | H81: =VLOOKUP(G81,'PUB 21'!$A$1:$B$29,2,0) -> FONDOS DEL SITUADO COORDINADO | M81: =CONCATENATE(TEXT(A81,"0"),"-",TEXT(C81,"0"),"-",TEXT(E81,"0"),"-",TEXT(LEFT(G81,2),"00"),"-",TEXT(RIGHT(G81,1),"0"),TEXT(I81,"0"),"-",TEXT(K81,"00")) -> 1-1-1-11-00-00 | N81: =IF(L81="",IF(J81="",IF(H81="",IF(F81="",IF(D81="",B81,D81),F81),H81),J81),L81) -> FONDOS DEL SITUADO COORDINADO | O81: =IF(P81="",0,IF(M80=M81,IF(O80="",0,O80)+1,"")) -> 4 | P81: VENEZUELA 0102-0792-23-0000078524 "A.M.L. SITUADO MCPAL. 2022" | Q81: =CONCATENATE(TEXT(A81,"0"),"-",TEXT(C81,"0"),"-",TEXT(E81,"0"),"-",TEXT(LEFT(G81,2),"00"),"-",TEXT(RIGHT(G81,1),"0"),TEXT(I81,"0"),"-",TEXT(K81,"00"),"-",TEXT(O81,"000")) -> 1-1-1-11-00-00-004 | R81: =IF(P81="",IF(L81="",IF(J81="",IF(H81="",IF(F81="",IF(D81="",B81,D81),F81),H81),J81),L81),P81) -> VENEZUELA 0102-0792-23-0000078524 "A.M.L. SITUADO MCPAL. 2022"
A82: 1 | B82: =VLOOKUP(A82,'ACTIVOS CODIGO'!A:B,2,0) -> ACTIVO | C82: 1 | D82: =VLOOKUP(C82,'ACTIVOS CODIGO'!C:D,2,0) -> ACTIVO DEL TESORO = ACTIVO CORRIENTE | E82: 2 | F82: =VLOOKUP(E82,'ACTIVOS CODIGO'!E:F,2,0) -> ACTIVO EXIGIBLE | G82: 120 | H82: =VLOOKUP(G82,'PUB 21'!$A$1:$B$29,2,0) -> DOCUMENTOS NEGOCIABLES | M82: =CONCATENATE(TEXT(A82,"0"),"-",TEXT(C82,"0"),"-",TEXT(E82,"0"),"-",TEXT(LEFT(G82,2),"00"),"-",TEXT(RIGHT(G82,1),"0"),TEXT(I82,"0"),"-",TEXT(K82,"00")) -> 1-1-2-12-00-00 | N82: =IF(L82="",IF(J82="",IF(H82="",IF(F82="",IF(D82="",B82,D82),F82),H82),J82),L82) -> DOCUMENTOS NEGOCIABLES | O82: =IF(P82="",0,IF(M81=M82,IF(O81="",0,O81)+1,"")) -> 0 | Q82: =CONCATENATE(TEXT(A82,"0"),"-",TEXT(C82,"0"),"-",TEXT(E82,"0"),"-",TEXT(LEFT(G82,2),"00"),"-",TEXT(RIGHT(G82,1),"0"),TEXT(I82,"0"),"-",TEXT(K82,"00"),"-",TEXT(O82,"000")) -> 1-1-2-12-00-00-000 | R82: =IF(P82="",IF(L82="",IF(J82="",IF(H82="",IF(F82="",IF(D82="",B82,D82),F82),H82),J82),L82),P82) -> DOCUMENTOS NEGOCIABLES
A83: 1 | B83: =VLOOKUP(A83,'ACTIVOS CODIGO'!A:B,2,0) -> ACTIVO | C83: 1 | D83: =VLOOKUP(C83,'ACTIVOS CODIGO'!C:D,2,0) -> ACTIVO DEL TESORO = ACTIVO CORRIENTE | E83: 2 | F83: =VLOOKUP(E83,'ACTIVOS CODIGO'!E:F,2,0) -> ACTIVO EXIGIBLE | G83: 122 | H83: =VLOOKUP(G83,'PUB 21'!$A$1:$B$29,2,0) -> INGRESOS POR RECAUDAR | M83: =CONCATENATE(TEXT(A83,"0"),"-",TEXT(C83,"0"),"-",TEXT(E83,"0"),"-",TEXT(LEFT(G83,2),"00"),"-",TEXT(RIGHT(G83,1),"0"),TEXT(I83,"0"),"-",TEXT(K83,"00")) -> 1-1-2-12-20-00 | N83: =IF(L83="",IF(J83="",IF(H83="",IF(F83="",IF(D83="",B83,D83),F83),H83),J83),L83) -> INGRESOS POR RECAUDAR | O83: =IF(P83="",0,IF(M82=M83,IF(O82="",0,O82)+1,"")) -> 0 | Q83: =CONCATENATE(TEXT(A83,"0"),"-",TEXT(C83,"0"),"-",TEXT(E83,"0"),"-",TEXT(LEFT(G83,2),"00"),"-",TEXT(RIGHT(G83,1),"0"),TEXT(I83,"0"),"-",TEXT(K83,"00"),"-",TEXT(O83,"000")) -> 1-1-2-12-20-00-000 | R83: =IF(P83="",IF(L83="",IF(J83="",IF(H83="",IF(F83="",IF(D83="",B83,D83),F83),H83),J83),L83),P83) -> INGRESOS POR RECAUDAR
A84: 1 | B84: =VLOOKUP(A84,'ACTIVOS CODIGO'!A:B,2,0) -> ACTIVO | C84: 1 | D84: =VLOOKUP(C84,'ACTIVOS CODIGO'!C:D,2,0) -> ACTIVO DEL TESORO = ACTIVO CORRIENTE | E84: 2 | F84: =VLOOKUP(E84,'ACTIVOS CODIGO'!E:F,2,0) -> ACTIVO EXIGIBLE | G84: 122 | H84: =VLOOKUP(G84,'PUB 21'!$A$1:$B$29,2,0) -> INGRESOS POR RECAUDAR | M84: =CONCATENATE(TEXT(A84,"0"),"-",TEXT(C84,"0"),"-",TEXT(E84,"0"),"-",TEXT(LEFT(G84,2),"00"),"-",TEXT(RIGHT(G84,1),"0"),TEXT(I84,"0"),"-",TEXT(K84,"00")) -> 1-1-2-12-20-00 | N84: =IF(L84="",IF(J84="",IF(H84="",IF(F84="",IF(D84="",B84,D84),F84),H84),J84),L84) -> INGRESOS POR RECAUDAR | O84: =IF(P84="",0,IF(M83=M84,IF(O83="",0,O83)+1,"")) -> 1 | P84: INGRESOS POR RECAUDAR 2008 | Q84: =CONCATENATE(TEXT(A84,"0"),"-",TEXT(C84,"0"),"-",TEXT(E84,"0"),"-",TEXT(LEFT(G84,2),"00"),"-",TEXT(RIGHT(G84,1),"0"),TEXT(I84,"0"),"-",TEXT(K84,"00"),"-",TEXT(O84,"000")) -> 1-1-2-12-20-00-001 | R84: =IF(P84="",IF(L84="",IF(J84="",IF(H84="",IF(F84="",IF(D84="",B84,D84),F84),H84),J84),L84),P84) -> INGRESOS POR RECAUDAR 2008
A85: 1 | B85: =VLOOKUP(A85,'ACTIVOS CODIGO'!A:B,2,0) -> ACTIVO | C85: 1 | D85: =VLOOKUP(C85,'ACTIVOS CODIGO'!C:D,2,0) -> ACTIVO DEL TESORO = ACTIVO CORRIENTE | E85: 2 | F85: =VLOOKUP(E85,'ACTIVOS CODIGO'!E:F,2,0) -> ACTIVO EXIGIBLE | G85: 122 | H85: =VLOOKUP(G85,'PUB 21'!$A$1:$B$29,2,0) -> INGRESOS POR RECAUDAR | M85: =CONCATENATE(TEXT(A85,"0"),"-",TEXT(C85,"0"),"-",TEXT(E85,"0"),"-",TEXT(LEFT(G85,2),"00"),"-",TEXT(RIGHT(G85,1),"0"),TEXT(I85,"0"),"-",TEXT(K85,"00")) -> 1-1-2-12-20-00 | N85: =IF(L85="",IF(J85="",IF(H85="",IF(F85="",IF(D85="",B85,D85),F85),H85),J85),L85) -> INGRESOS POR RECAUDAR | O85: =IF(P85="",0,IF(M84=M85,IF(O84="",0,O84)+1,"")) -> 2 | P85: SITUADO MUNICIPAL 2019 | Q85: =CONCATENATE(TEXT(A85,"0"),"-",TEXT(C85,"0"),"-",TEXT(E85,"0"),"-",TEXT(LEFT(G85,2),"00"),"-",TEXT(RIGHT(G85,1),"0"),TEXT(I85,"0"),"-",TEXT(K85,"00"),"-",TEXT(O85,"000")) -> 1-1-2-12-20-00-002 | R85: =IF(P85="",IF(L85="",IF(J85="",IF(H85="",IF(F85="",IF(D85="",B85,D85),F85),H85),J85),L85),P85) -> SITUADO MUNICIPAL 2019
A86: 1 | B86: =VLOOKUP(A86,'ACTIVOS CODIGO'!A:B,2,0) -> ACTIVO | C86: 1 | D86: =VLOOKUP(C86,'ACTIVOS CODIGO'!C:D,2,0) -> ACTIVO DEL TESORO = ACTIVO CORRIENTE | E86: 2 | F86: =VLOOKUP(E86,'ACTIVOS CODIGO'!E:F,2,0) -> ACTIVO EXIGIBLE | G86: 122 | H86: =VLOOKUP(G86,'PUB 21'!$A$1:$B$29,2,0) -> INGRESOS POR RECAUDAR | M86: =CONCATENATE(TEXT(A86,"0"),"-",TEXT(C86,"0"),"-",TEXT(E86,"0"),"-",TEXT(LEFT(G86,2),"00"),"-",TEXT(RIGHT(G86,1),"0"),TEXT(I86,"0"),"-",TEXT(K86,"00")) -> 1-1-2-12-20-00 | N86: =IF(L86="",IF(J86="",IF(H86="",IF(F86="",IF(D86="",B86,D86),F86),H86),J86),L86) -> INGRESOS POR RECAUDAR | O86: =IF(P86="",0,IF(M85=M86,IF(O85="",0,O85)+1,"")) -> 3 | P86: INGRESOS POR RECAUDAR 2020 | Q86: =CONCATENATE(TEXT(A86,"0"),"-",TEXT(C86,"0"),"-",TEXT(E86,"0"),"-",TEXT(LEFT(G86,2),"00"),"-",TEXT(RIGHT(G86,1),"0"),TEXT(I86,"0"),"-",TEXT(K86,"00"),"-",TEXT(O86,"000")) -> 1-1-2-12-20-00-003 | R86: =IF(P86="",IF(L86="",IF(J86="",IF(H86="",IF(F86="",IF(D86="",B86,D86),F86),H86),J86),L86),P86) -> INGRESOS POR RECAUDAR 2020
A87: 1 | B87: =VLOOKUP(A87,'ACTIVOS CODIGO'!A:B,2,0) -> ACTIVO | C87: 1 | D87: =VLOOKUP(C87,'ACTIVOS CODIGO'!C:D,2,0) -> ACTIVO DEL TESORO = ACTIVO CORRIENTE | E87: 2 | F87: =VLOOKUP(E87,'ACTIVOS CODIGO'!E:F,2,0) -> ACTIVO EXIGIBLE | G87: 122 | H87: =VLOOKUP(G87,'PUB 21'!$A$1:$B$29,2,0) -> INGRESOS POR RECAUDAR | M87: =CONCATENATE(TEXT(A87,"0"),"-",TEXT(C87,"0"),"-",TEXT(E87,"0"),"-",TEXT(LEFT(G87,2),"00"),"-",TEXT(RIGHT(G87,1),"0"),TEXT(I87,"0"),"-",TEXT(K87,"00")) -> 1-1-2-12-20-00 | N87: =IF(L87="",IF(J87="",IF(H87="",IF(F87="",IF(D87="",B87,D87),F87),H87),J87),L87) -> INGRESOS POR RECAUDAR | O87: =IF(P87="",0,IF(M86=M87,IF(O86="",0,O86)+1,"")) -> 4 | P87: INGRESOS POR RECAUDAR 2021 | Q87: =CONCATENATE(TEXT(A87,"0"),"-",TEXT(C87,"0"),"-",TEXT(E87,"0"),"-",TEXT(LEFT(G87,2),"00"),"-",TEXT(RIGHT(G87,1),"0"),TEXT(I87,"0"),"-",TEXT(K87,"00"),"-",TEXT(O87,"000")) -> 1-1-2-12-20-00-004 | R87: =IF(P87="",IF(L87="",IF(J87="",IF(H87="",IF(F87="",IF(D87="",B87,D87),F87),H87),J87),L87),P87) -> INGRESOS POR RECAUDAR 2021
A88: 1 | B88: =VLOOKUP(A88,'ACTIVOS CODIGO'!A:B,2,0) -> ACTIVO | C88: 1 | D88: =VLOOKUP(C88,'ACTIVOS CODIGO'!C:D,2,0) -> ACTIVO DEL TESORO = ACTIVO CORRIENTE | E88: 2 | F88: =VLOOKUP(E88,'ACTIVOS CODIGO'!E:F,2,0) -> ACTIVO EXIGIBLE | G88: 122 | H88: =VLOOKUP(G88,'PUB 21'!$A$1:$B$29,2,0) -> INGRESOS POR RECAUDAR | M88: =CONCATENATE(TEXT(A88,"0"),"-",TEXT(C88,"0"),"-",TEXT(E88,"0"),"-",TEXT(LEFT(G88,2),"00"),"-",TEXT(RIGHT(G88,1),"0"),TEXT(I88,"0"),"-",TEXT(K88,"00")) -> 1-1-2-12-20-00 | N88: =IF(L88="",IF(J88="",IF(H88="",IF(F88="",IF(D88="",B88,D88),F88),H88),J88),L88) -> INGRESOS POR RECAUDAR | O88: =IF(P88="",0,IF(M87=M88,IF(O87="",0,O87)+1,"")) -> 5 | P88: INGRESOS POR RECAUDAR SITUADO MUNICIPAL 2021 | Q88: =CONCATENATE(TEXT(A88,"0"),"-",TEXT(C88,"0"),"-",TEXT(E88,"0"),"-",TEXT(LEFT(G88,2),"00"),"-",TEXT(RIGHT(G88,1),"0"),TEXT(I88,"0"),"-",TEXT(K88,"00"),"-",TEXT(O88,"000")) -> 1-1-2-12-20-00-005 | R88: =IF(P88="",IF(L88="",IF(J88="",IF(H88="",IF(F88="",IF(D88="",B88,D88),F88),H88),J88),L88),P88) -> INGRESOS POR RECAUDAR SITUADO MUNICIPAL 2021
A89: 1 | B89: =VLOOKUP(A89,'ACTIVOS CODIGO'!A:B,2,0) -> ACTIVO | C89: 1 | D89: =VLOOKUP(C89,'ACTIVOS CODIGO'!C:D,2,0) -> ACTIVO DEL TESORO = ACTIVO CORRIENTE | E89: 2 | F89: =VLOOKUP(E89,'ACTIVOS CODIGO'!E:F,2,0) -> ACTIVO EXIGIBLE | G89: 122 | H89: =VLOOKUP(G89,'PUB 21'!$A$1:$B$29,2,0) -> INGRESOS POR RECAUDAR | M89: =CONCATENATE(TEXT(A89,"0"),"-",TEXT(C89,"0"),"-",TEXT(E89,"0"),"-",TEXT(LEFT(G89,2),"00"),"-",TEXT(RIGHT(G89,1),"0"),TEXT(I89,"0"),"-",TEXT(K89,"00")) -> 1-1-2-12-20-00 | N89: =IF(L89="",IF(J89="",IF(H89="",IF(F89="",IF(D89="",B89,D89),F89),H89),J89),L89) -> INGRESOS POR RECAUDAR | O89: =IF(P89="",0,IF(M88=M89,IF(O88="",0,O88)+1,"")) -> 6 | P89: INGRESOS POR RECAUDAR 2009 | Q89: =CONCATENATE(TEXT(A89,"0"),"-",TEXT(C89,"0"),"-",TEXT(E89,"0"),"-",TEXT(LEFT(G89,2),"00"),"-",TEXT(RIGHT(G89,1),"0"),TEXT(I89,"0"),"-",TEXT(K89,"00"),"-",TEXT(O89,"000")) -> 1-1-2-12-20-00-006 | R89: =IF(P89="",IF(L89="",IF(J89="",IF(H89="",IF(F89="",IF(D89="",B89,D89),F89),H89),J89),L89),P89) -> INGRESOS POR RECAUDAR 2009
A90: 1 | B90: =VLOOKUP(A90,'ACTIVOS CODIGO'!A:B,2,0) -> ACTIVO | C90: 1 | D90: =VLOOKUP(C90,'ACTIVOS CODIGO'!C:D,2,0) -> ACTIVO DEL TESORO = ACTIVO CORRIENTE | E90: 2 | F90: =VLOOKUP(E90,'ACTIVOS CODIGO'!E:F,2,0) -> ACTIVO EXIGIBLE | G90: 122 | H90: =VLOOKUP(G90,'PUB 21'!$A$1:$B$29,2,0) -> INGRESOS POR RECAUDAR | M90: =CONCATENATE(TEXT(A90,"0"),"-",TEXT(C90,"0"),"-",TEXT(E90,"0"),"-",TEXT(LEFT(G90,2),"00"),"-",TEXT(RIGHT(G90,1),"0"),TEXT(I90,"0"),"-",TEXT(K90,"00")) -> 1-1-2-12-20-00 | N90: =IF(L90="",IF(J90="",IF(H90="",IF(F90="",IF(D90="",B90,D90),F90),H90),J90),L90) -> INGRESOS POR RECAUDAR | O90: =IF(P90="",0,IF(M89=M90,IF(O89="",0,O89)+1,"")) -> 7 | P90: INGRESOS POR RECAUDAR BANESCO | Q90: =CONCATENATE(TEXT(A90,"0"),"-",TEXT(C90,"0"),"-",TEXT(E90,"0"),"-",TEXT(LEFT(G90,2),"00"),"-",TEXT(RIGHT(G90,1),"0"),TEXT(I90,"0"),"-",TEXT(K90,"00"),"-",TEXT(O90,"000")) -> 1-1-2-12-20-00-007 | R90: =IF(P90="",IF(L90="",IF(J90="",IF(H90="",IF(F90="",IF(D90="",B90,D90),F90),H90),J90),L90),P90) -> INGRESOS POR RECAUDAR BANESCO
A91: 1 | B91: =VLOOKUP(A91,'ACTIVOS CODIGO'!A:B,2,0) -> ACTIVO | C91: 1 | D91: =VLOOKUP(C91,'ACTIVOS CODIGO'!C:D,2,0) -> ACTIVO DEL TESORO = ACTIVO CORRIENTE | E91: 2 | F91: =VLOOKUP(E91,'ACTIVOS CODIGO'!E:F,2,0) -> ACTIVO EXIGIBLE | G91: 122 | H91: =VLOOKUP(G91,'PUB 21'!$A$1:$B$29,2,0) -> INGRESOS POR RECAUDAR | M91: =CONCATENATE(TEXT(A91,"0"),"-",TEXT(C91,"0"),"-",TEXT(E91,"0"),"-",TEXT(LEFT(G91,2),"00"),"-",TEXT(RIGHT(G91,1),"0"),TEXT(I91,"0"),"-",TEXT(K91,"00")) -> 1-1-2-12-20-00 | N91: =IF(L91="",IF(J91="",IF(H91="",IF(F91="",IF(D91="",B91,D91),F91),H91),J91),L91) -> INGRESOS POR RECAUDAR | O91: =IF(P91="",0,IF(M90=M91,IF(O90="",0,O90)+1,"")) -> 8 | P91: ING. X RECAUDAR PROVINCIAL 2018 | Q91: =CONCATENATE(TEXT(A91,"0"),"-",TEXT(C91,"0"),"-",TEXT(E91,"0"),"-",TEXT(LEFT(G91,2),"00"),"-",TEXT(RIGHT(G91,1),"0"),TEXT(I91,"0"),"-",TEXT(K91,"00"),"-",TEXT(O91,"000")) -> 1-1-2-12-20-00-008 | R91: =IF(P91="",IF(L91="",IF(J91="",IF(H91="",IF(F91="",IF(D91="",B91,D91),F91),H91),J91),L91),P91) -> ING. X RECAUDAR PROVINCIAL 2018
A92: 1 | B92: =VLOOKUP(A92,'ACTIVOS CODIGO'!A:B,2,0) -> ACTIVO | C92: 1 | D92: =VLOOKUP(C92,'ACTIVOS CODIGO'!C:D,2,0) -> ACTIVO DEL TESORO = ACTIVO CORRIENTE | E92: 2 | F92: =VLOOKUP(E92,'ACTIVOS CODIGO'!E:F,2,0) -> ACTIVO EXIGIBLE | G92: 122 | H92: =VLOOKUP(G92,'PUB 21'!$A$1:$B$29,2,0) -> INGRESOS POR RECAUDAR | M92: =CONCATENATE(TEXT(A92,"0"),"-",TEXT(C92,"0"),"-",TEXT(E92,"0"),"-",TEXT(LEFT(G92,2),"00"),"-",TEXT(RIGHT(G92,1),"0"),TEXT(I92,"0"),"-",TEXT(K92,"00")) -> 1-1-2-12-20-00 | N92: =IF(L92="",IF(J92="",IF(H92="",IF(F92="",IF(D92="",B92,D92),F92),H92),J92),L92) -> INGRESOS POR RECAUDAR | O92: =IF(P92="",0,IF(M91=M92,IF(O91="",0,O91)+1,"")) -> 9 | P92: PARTIDAS POR CERTIFICAR BANCO DE VENEZUELA | Q92: =CONCATENATE(TEXT(A92,"0"),"-",TEXT(C92,"0"),"-",TEXT(E92,"0"),"-",TEXT(LEFT(G92,2),"00"),"-",TEXT(RIGHT(G92,1),"0"),TEXT(I92,"0"),"-",TEXT(K92,"00"),"-",TEXT(O92,"000")) -> 1-1-2-12-20-00-009 | R92: =IF(P92="",IF(L92="",IF(J92="",IF(H92="",IF(F92="",IF(D92="",B92,D92),F92),H92),J92),L92),P92) -> PARTIDAS POR CERTIFICAR BANCO DE VENEZUELA
A93: 1 | B93: =VLOOKUP(A93,'ACTIVOS CODIGO'!A:B,2,0) -> ACTIVO | C93: 1 | D93: =VLOOKUP(C93,'ACTIVOS CODIGO'!C:D,2,0) -> ACTIVO DEL TESORO = ACTIVO CORRIENTE | E93: 2 | F93: =VLOOKUP(E93,'ACTIVOS CODIGO'!E:F,2,0) -> ACTIVO EXIGIBLE | G93: 122 | H93: =VLOOKUP(G93,'PUB 21'!$A$1:$B$29,2,0) -> INGRESOS POR RECAUDAR | M93: =CONCATENATE(TEXT(A93,"0"),"-",TEXT(C93,"0"),"-",TEXT(E93,"0"),"-",TEXT(LEFT(G93,2),"00"),"-",TEXT(RIGHT(G93,1),"0"),TEXT(I93,"0"),"-",TEXT(K93,"00")) -> 1-1-2-12-20-00 | N93: =IF(L93="",IF(J93="",IF(H93="",IF(F93="",IF(D93="",B93,D93),F93),H93),J93),L93) -> INGRESOS POR RECAUDAR | O93: =IF(P93="",0,IF(M92=M93,IF(O92="",0,O92)+1,"")) -> 10 | P93: ING. POR RECAUDAR TESORO 2018 | Q93: =CONCATENATE(TEXT(A93,"0"),"-",TEXT(C93,"0"),"-",TEXT(E93,"0"),"-",TEXT(LEFT(G93,2),"00"),"-",TEXT(RIGHT(G93,1),"0"),TEXT(I93,"0"),"-",TEXT(K93,"00"),"-",TEXT(O93,"000")) -> 1-1-2-12-20-00-010 | R93: =IF(P93="",IF(L93="",IF(J93="",IF(H93="",IF(F93="",IF(D93="",B93,D93),F93),H93),J93),L93),P93) -> ING. POR RECAUDAR TESORO 2018
A94: 1 | B94: =VLOOKUP(A94,'ACTIVOS CODIGO'!A:B,2,0) -> ACTIVO | C94: 1 | D94: =VLOOKUP(C94,'ACTIVOS CODIGO'!C:D,2,0) -> ACTIVO DEL TESORO = ACTIVO CORRIENTE | E94: 2 | F94: =VLOOKUP(E94,'ACTIVOS CODIGO'!E:F,2,0) -> ACTIVO EXIGIBLE | G94: 122 | H94: =VLOOKUP(G94,'PUB 21'!$A$1:$B$29,2,0) -> INGRESOS POR RECAUDAR | M94: =CONCATENATE(TEXT(A94,"0"),"-",TEXT(C94,"0"),"-",TEXT(E94,"0"),"-",TEXT(LEFT(G94,2),"00"),"-",TEXT(RIGHT(G94,1),"0"),TEXT(I94,"0"),"-",TEXT(K94,"00")) -> 1-1-2-12-20-00 | N94: =IF(L94="",IF(J94="",IF(H94="",IF(F94="",IF(D94="",B94,D94),F94),H94),J94),L94) -> INGRESOS POR RECAUDAR | O94: =IF(P94="",0,IF(M93=M94,IF(O93="",0,O93)+1,"")) -> 11 | P94: INGRESOS POR RECAUDAR IMCP 98545 | Q94: =CONCATENATE(TEXT(A94,"0"),"-",TEXT(C94,"0"),"-",TEXT(E94,"0"),"-",TEXT(LEFT(G94,2),"00"),"-",TEXT(RIGHT(G94,1),"0"),TEXT(I94,"0"),"-",TEXT(K94,"00"),"-",TEXT(O94,"000")) -> 1-1-2-12-20-00-011 | R94: =IF(P94="",IF(L94="",IF(J94="",IF(H94="",IF(F94="",IF(D94="",B94,D94),F94),H94),J94),L94),P94) -> INGRESOS POR RECAUDAR IMCP 98545
A95: 1 | B95: =VLOOKUP(A95,'ACTIVOS CODIGO'!A:B,2,0) -> ACTIVO | C95: 1 | D95: =VLOOKUP(C95,'ACTIVOS CODIGO'!C:D,2,0) -> ACTIVO DEL TESORO = ACTIVO CORRIENTE | E95: 2 | F95: =VLOOKUP(E95,'ACTIVOS CODIGO'!E:F,2,0) -> ACTIVO EXIGIBLE | G95: 122 | H95: =VLOOKUP(G95,'PUB 21'!$A$1:$B$29,2,0) -> INGRESOS POR RECAUDAR | M95: =CONCATENATE(TEXT(A95,"0"),"-",TEXT(C95,"0"),"-",TEXT(E95,"0"),"-",TEXT(LEFT(G95,2),"00"),"-",TEXT(RIGHT(G95,1),"0"),TEXT(I95,"0"),"-",TEXT(K95,"00")) -> 1-1-2-12-20-00 | N95: =IF(L95="",IF(J95="",IF(H95="",IF(F95="",IF(D95="",B95,D95),F95),H95),J95),L95) -> INGRESOS POR RECAUDAR | O95: =IF(P95="",0,IF(M94=M95,IF(O94="",0,O94)+1,"")) -> 12 | P95: INGRESOS POR RECAUDAR BNC | Q95: =CONCATENATE(TEXT(A95,"0"),"-",TEXT(C95,"0"),"-",TEXT(E95,"0"),"-",TEXT(LEFT(G95,2),"00"),"-",TEXT(RIGHT(G95,1),"0"),TEXT(I95,"0"),"-",TEXT(K95,"00"),"-",TEXT(O95,"000")) -> 1-1-2-12-20-00-012 | R95: =IF(P95="",IF(L95="",IF(J95="",IF(H95="",IF(F95="",IF(D95="",B95,D95),F95),H95),J95),L95),P95) -> INGRESOS POR RECAUDAR BNC
... A98: 1 | B98: =VLOOKUP(A98,'ACTIVOS CODIGO'!A:B,2,0) -> ACTIVO | C98: 1 | D98: =VLOOKUP(C98,'ACTIVOS CODIGO'!C:D,2,0) -> ACTIVO DEL TESORO = ACTIVO CORRIENTE | E98: 2 | F98: =VLOOKUP(E98,'ACTIVOS CODIGO'!E:F,2,0) -> ACTIVO EXIGIBLE | G98: 122 | H98: =VLOOKUP(G98,'PUB 21'!$A$1:$B$29,2,0) -> INGRESOS POR RECAUDAR | M98: =CONCATENATE(TEXT(A98,"0"),"-",TEXT(C98,"0"),"-",TEXT(E98,"0"),"-",TEXT(LEFT(G98,2),"00"),"-",TEXT(RIGHT(G98,1),"0"),TEXT(I98,"0"),"-",TEXT(K98,"00")) -> 1-1-2-12-20-00 | N98: =IF(L98="",IF(J98="",IF(H98="",IF(F98="",IF(D98="",B98,D98),F98),H98),J98),L98) -> INGRESOS POR RECAUDAR | O98: =IF(P98="",0,IF(M97=M98,IF(O97="",0,O97)+1,"")) -> 15 | P98: INGRESOS POR RECAUDAR BANCAMIGA | Q98: =CONCATENATE(TEXT(A98,"0"),"-",TEXT(C98,"0"),"-",TEXT(E98,"0"),"-",TEXT(LEFT(G98,2),"00"),"-",TEXT(RIGHT(G98,1),"0"),TEXT(I98,"0"),"-",TEXT(K98,"00"),"-",TEXT(O98,"000")) -> 1-1-2-12-20-00-015 | R98: =IF(P98="",IF(L98="",IF(J98="",IF(H98="",IF(F98="",IF(D98="",B98,D98),F98),H98),J98),L98),P98) -> INGRESOS POR RECAUDAR BANCAMIGA
A99: 1 | B99: =VLOOKUP(A99,'ACTIVOS CODIGO'!A:B,2,0) -> ACTIVO | C99: 1 | D99: =VLOOKUP(C99,'ACTIVOS CODIGO'!C:D,2,0) -> ACTIVO DEL TESORO = ACTIVO CORRIENTE | E99: 2 | F99: =VLOOKUP(E99,'ACTIVOS CODIGO'!E:F,2,0) -> ACTIVO EXIGIBLE | G99: 126 | H99: =VLOOKUP(G99,'PUB 21'!$A$1:$B$29,2,0) -> FONDOS EN AVANCE | M99: =CONCATENATE(TEXT(A99,"0"),"-",TEXT(C99,"0"),"-",TEXT(E99,"0"),"-",TEXT(LEFT(G99,2),"00"),"-",TEXT(RIGHT(G99,1),"0"),TEXT(I99,"0"),"-",TEXT(K99,"00")) -> 1-1-2-12-60-00 | N99: =IF(L99="",IF(J99="",IF(H99="",IF(F99="",IF(D99="",B99,D99),F99),H99),J99),L99) -> FONDOS EN AVANCE | O99: =IF(P99="",0,IF(M98=M99,IF(O98="",0,O98)+1,"")) -> 0 | Q99: =CONCATENATE(TEXT(A99,"0"),"-",TEXT(C99,"0"),"-",TEXT(E99,"0"),"-",TEXT(LEFT(G99,2),"00"),"-",TEXT(RIGHT(G99,1),"0"),TEXT(I99,"0"),"-",TEXT(K99,"00"),"-",TEXT(O99,"000")) -> 1-1-2-12-60-00-000 | R99: =IF(P99="",IF(L99="",IF(J99="",IF(H99="",IF(F99="",IF(D99="",B99,D99),F99),H99),J99),L99),P99) -> FONDOS EN AVANCE
A100: 1 | B100: =VLOOKUP(A100,'ACTIVOS CODIGO'!A:B,2,0) -> ACTIVO | C100: 1 | D100: =VLOOKUP(C100,'ACTIVOS CODIGO'!C:D,2,0) -> ACTIVO DEL TESORO = ACTIVO CORRIENTE | E100: 2 | F100: =VLOOKUP(E100,'ACTIVOS CODIGO'!E:F,2,0) -> ACTIVO EXIGIBLE | G100: 126 | H100: =VLOOKUP(G100,'PUB 21'!$A$1:$B$29,2,0) -> FONDOS EN AVANCE | M100: =CONCATENATE(TEXT(A100,"0"),"-",TEXT(C100,"0"),"-",TEXT(E100,"0"),"-",TEXT(LEFT(G100,2),"00"),"-",TEXT(RIGHT(G100,1),"0"),TEXT(I100,"0"),"-",TEXT(K100,"00")) -> 1-1-2-12-60-00 | N100: =IF(L100="",IF(J100="",IF(H100="",IF(F100="",IF(D100="",B100,D100),F100),H100),J100),L100) -> FONDOS EN AVANCE | O100: =IF(P100="",0,IF(M99=M100,IF(O99="",0,O99)+1,"")) -> 1 | P100: FONDOS EN AVANCE 2012 | Q100: =CONCATENATE(TEXT(A100,"0"),"-",TEXT(C100,"0"),"-",TEXT(E100,"0"),"-",TEXT(LEFT(G100,2),"00"),"-",TEXT(RIGHT(G100,1),"0"),TEXT(I100,"0"),"-",TEXT(K100,"00"),"-",TEXT(O100,"000")) -> 1-1-2-12-60-00-001 | R100: =IF(P100="",IF(L100="",IF(J100="",IF(H100="",IF(F100="",IF(D100="",B100,D100),F100),H100),J100),L100),P100) -> FONDOS EN AVANCE 2012
A101: 1 | B101: =VLOOKUP(A101,'ACTIVOS CODIGO'!A:B,2,0) -> ACTIVO | C101: 1 | D101: =VLOOKUP(C101,'ACTIVOS CODIGO'!C:D,2,0) -> ACTIVO DEL TESORO = ACTIVO CORRIENTE | E101: 2 | F101: =VLOOKUP(E101,'ACTIVOS CODIGO'!E:F,2,0) -> ACTIVO EXIGIBLE | G101: 126 | H101: =VLOOKUP(G101,'PUB 21'!$A$1:$B$29,2,0) -> FONDOS EN AVANCE | M101: =CONCATENATE(TEXT(A101,"0"),"-",TEXT(C101,"0"),"-",TEXT(E101,"0"),"-",TEXT(LEFT(G101,2),"00"),"-",TEXT(RIGHT(G101,1),"0"),TEXT(I101,"0"),"-",TEXT(K101,"00")) -> 1-1-2-12-60-00 | N101: =IF(L101="",IF(J101="",IF(H101="",IF(F101="",IF(D101="",B101,D101),F101),H101),J101),L101) -> FONDOS EN AVANCE | O101: =IF(P101="",0,IF(M100=M101,IF(O100="",0,O100)+1,"")) -> 2 | P101: FONDOS ADMINISTRADOS DE SALUD | Q101: =CONCATENATE(TEXT(A101,"0"),"-",TEXT(C101,"0"),"-",TEXT(E101,"0"),"-",TEXT(LEFT(G101,2),"00"),"-",TEXT(RIGHT(G101,1),"0"),TEXT(I101,"0"),"-",TEXT(K101,"00"),"-",TEXT(O101,"000")) -> 1-1-2-12-60-00-002 | R101: =IF(P101="",IF(L101="",IF(J101="",IF(H101="",IF(F101="",IF(D101="",B101,D101),F101),H101),J101),L101),P101) -> FONDOS ADMINISTRADOS DE SALUD
A102: 1 | B102: =VLOOKUP(A102,'ACTIVOS CODIGO'!A:B,2,0) -> ACTIVO | C102: 1 | D102: =VLOOKUP(C102,'ACTIVOS CODIGO'!C:D,2,0) -> ACTIVO DEL TESORO = ACTIVO CORRIENTE | E102: 2 | F102: =VLOOKUP(E102,'ACTIVOS CODIGO'!E:F,2,0) -> ACTIVO EXIGIBLE | G102: 126 | H102: =VLOOKUP(G102,'PUB 21'!$A$1:$B$29,2,0) -> FONDOS EN AVANCE | M102: =CONCATENATE(TEXT(A102,"0"),"-",TEXT(C102,"0"),"-",TEXT(E102,"0"),"-",TEXT(LEFT(G102,2),"00"),"-",TEXT(RIGHT(G102,1),"0"),TEXT(I102,"0"),"-",TEXT(K102,"00")) -> 1-1-2-12-60-00 | N102: =IF(L102="",IF(J102="",IF(H102="",IF(F102="",IF(D102="",B102,D102),F102),H102),J102),L102) -> FONDOS EN AVANCE | O102: =IF(P102="",0,IF(M101=M102,IF(O101="",0,O101)+1,"")) -> 3 | P102: FONDOS EN AVANCE 2013 | Q102: =CONCATENATE(TEXT(A102,"0"),"-",TEXT(C102,"0"),"-",TEXT(E102,"0"),"-",TEXT(LEFT(G102,2),"00"),"-",TEXT(RIGHT(G102,1),"0"),TEXT(I102,"0"),"-",TEXT(K102,"00"),"-",TEXT(O102,"000")) -> 1-1-2-12-60-00-003 | R102: =IF(P102="",IF(L102="",IF(J102="",IF(H102="",IF(F102="",IF(D102="",B102,D102),F102),H102),J102),L102),P102) -> FONDOS EN AVANCE 2013
A103: 1 | B103: =VLOOKUP(A103,'ACTIVOS CODIGO'!A:B,2,0) -> ACTIVO | C103: 1 | D103: =VLOOKUP(C103,'ACTIVOS CODIGO'!C:D,2,0) -> ACTIVO DEL TESORO = ACTIVO CORRIENTE | E103: 2 | F103: =VLOOKUP(E103,'ACTIVOS CODIGO'!E:F,2,0) -> ACTIVO EXIGIBLE | G103: 126 | H103: =VLOOKUP(G103,'PUB 21'!$A$1:$B$29,2,0) -> FONDOS EN AVANCE | M103: =CONCATENATE(TEXT(A103,"0"),"-",TEXT(C103,"0"),"-",TEXT(E103,"0"),"-",TEXT(LEFT(G103,2),"00"),"-",TEXT(RIGHT(G103,1),"0"),TEXT(I103,"0"),"-",TEXT(K103,"00")) -> 1-1-2-12-60-00 | N103: =IF(L103="",IF(J103="",IF(H103="",IF(F103="",IF(D103="",B103,D103),F103),H103),J103),L103) -> FONDOS EN AVANCE | O103: =IF(P103="",0,IF(M102=M103,IF(O102="",0,O102)+1,"")) -> 4 | P103: FONDOS ADMI. DE SALUD 2013 | Q103: =CONCATENATE(TEXT(A103,"0"),"-",TEXT(C103,"0"),"-",TEXT(E103,"0"),"-",TEXT(LEFT(G103,2),"00"),"-",TEXT(RIGHT(G103,1),"0"),TEXT(I103,"0"),"-",TEXT(K103,"00"),"-",TEXT(O103,"000")) -> 1-1-2-12-60-00-004 | R103: =IF(P103="",IF(L103="",IF(J103="",IF(H103="",IF(F103="",IF(D103="",B103,D103),F103),H103),J103),L103),P103) -> FONDOS ADMI. DE SALUD 2013
A104: 1 | B104: =VLOOKUP(A104,'ACTIVOS CODIGO'!A:B,2,0) -> ACTIVO | C104: 1 | D104: =VLOOKUP(C104,'ACTIVOS CODIGO'!C:D,2,0) -> ACTIVO DEL TESORO = ACTIVO CORRIENTE | E104: 2 | F104: =VLOOKUP(E104,'ACTIVOS CODIGO'!E:F,2,0) -> ACTIVO EXIGIBLE | G104: 126 | H104: =VLOOKUP(G104,'PUB 21'!$A$1:$B$29,2,0) -> FONDOS EN AVANCE | M104: =CONCATENATE(TEXT(A104,"0"),"-",TEXT(C104,"0"),"-",TEXT(E104,"0"),"-",TEXT(LEFT(G104,2),"00"),"-",TEXT(RIGHT(G104,1),"0"),TEXT(I104,"0"),"-",TEXT(K104,"00")) -> 1-1-2-12-60-00 | N104: =IF(L104="",IF(J104="",IF(H104="",IF(F104="",IF(D104="",B104,D104),F104),H104),J104),L104) -> FONDOS EN AVANCE | O104: =IF(P104="",0,IF(M103=M104,IF(O103="",0,O103)+1,"")) -> 5 | P104: FONDOS EN AVANCE 2018 | Q104: =CONCATENATE(TEXT(A104,"0"),"-",TEXT(C104,"0"),"-",TEXT(E104,"0"),"-",TEXT(LEFT(G104,2),"00"),"-",TEXT(RIGHT(G104,1),"0"),TEXT(I104,"0"),"-",TEXT(K104,"00"),"-",TEXT(O104,"000")) -> 1-1-2-12-60-00-005 | R104: =IF(P104="",IF(L104="",IF(J104="",IF(H104="",IF(F104="",IF(D104="",B104,D104),F104),H104),J104),L104),P104) -> FONDOS EN AVANCE 2018
A105: 1 | B105: =VLOOKUP(A105,'ACTIVOS CODIGO'!A:B,2,0) -> ACTIVO | C105: 1 | D105: =VLOOKUP(C105,'ACTIVOS CODIGO'!C:D,2,0) -> ACTIVO DEL TESORO = ACTIVO CORRIENTE | E105: 2 | F105: =VLOOKUP(E105,'ACTIVOS CODIGO'!E:F,2,0) -> ACTIVO EXIGIBLE | G105: 126 | H105: =VLOOKUP(G105,'PUB 21'!$A$1:$B$29,2,0) -> FONDOS EN AVANCE | M105: =CONCATENATE(TEXT(A105,"0"),"-",TEXT(C105,"0"),"-",TEXT(E105,"0"),"-",TEXT(LEFT(G105,2),"00"),"-",TEXT(RIGHT(G105,1),"0"),TEXT(I105,"0"),"-",TEXT(K105,"00")) -> 1-1-2-12-60-00 | N105: =IF(L105="",IF(J105="",IF(H105="",IF(F105="",IF(D105="",B105,D105),F105),H105),J105),L105) -> FONDOS EN AVANCE | O105: =IF(P105="",0,IF(M104=M105,IF(O104="",0,O104)+1,"")) -> 6 | P105: SINDICATURA MUNICIPAL 2018 | Q105: =CONCATENATE(TEXT(A105,"0"),"-",TEXT(C105,"0"),"-",TEXT(E105,"0"),"-",TEXT(LEFT(G105,2),"00"),"-",TEXT(RIGHT(G105,1),"0"),TEXT(I105,"0"),"-",TEXT(K105,"00"),"-",TEXT(O105,"000")) -> 1-1-2-12-60-00-006 | R105: =IF(P105="",IF(L105="",IF(J105="",IF(H105="",IF(F105="",IF(D105="",B105,D105),F105),H105),J105),L105),P105) -> SINDICATURA MUNICIPAL 2018
A106: 1 | B106: =VLOOKUP(A106,'ACTIVOS CODIGO'!A:B,2,0) -> ACTIVO | C106: 1 | D106: =VLOOKUP(C106,'ACTIVOS CODIGO'!C:D,2,0) -> ACTIVO DEL TESORO = ACTIVO CORRIENTE | E106: 2 | F106: =VLOOKUP(E106,'ACTIVOS CODIGO'!E:F,2,0) -> ACTIVO EXIGIBLE | G106: 126 | H106: =VLOOKUP(G106,'PUB 21'!$A$1:$B$29,2,0) -> FONDOS EN AVANCE | M106: =CONCATENATE(TEXT(A106,"0"),"-",TEXT(C106,"0"),"-",TEXT(E106,"0"),"-",TEXT(LEFT(G106,2),"00"),"-",TEXT(RIGHT(G106,1),"0"),TEXT(I106,"0"),"-",TEXT(K106,"00")) -> 1-1-2-12-60-00 | N106: =IF(L106="",IF(J106="",IF(H106="",IF(F106="",IF(D106="",B106,D106),F106),H106),J106),L106) -> FONDOS EN AVANCE | O106: =IF(P106="",0,IF(M105=M106,IF(O105="",0,O105)+1,"")) -> 7 | P106: DIRECCION DE RECURSOS HUMANOS 2018 | Q106: =CONCATENATE(TEXT(A106,"0"),"-",TEXT(C106,"0"),"-",TEXT(E106,"0"),"-",TEXT(LEFT(G106,2),"00"),"-",TEXT(RIGHT(G106,1),"0"),TEXT(I106,"0"),"-",TEXT(K106,"00"),"-",TEXT(O106,"000")) -> 1-1-2-12-60-00-007 | R106: =IF(P106="",IF(L106="",IF(J106="",IF(H106="",IF(F106="",IF(D106="",B106,D106),F106),H106),J106),L106),P106) -> DIRECCION DE RECURSOS HUMANOS 2018
A107: 1 | B107: =VLOOKUP(A107,'ACTIVOS CODIGO'!A:B,2,0) -> ACTIVO | C107: 1 | D107: =VLOOKUP(C107,'ACTIVOS CODIGO'!C:D,2,0) -> ACTIVO DEL TESORO = ACTIVO CORRIENTE | E107: 2 | F107: =VLOOKUP(E107,'ACTIVOS CODIGO'!E:F,2,0) -> ACTIVO EXIGIBLE | G107: 126 | H107: =VLOOKUP(G107,'PUB 21'!$A$1:$B$29,2,0) -> FONDOS EN AVANCE | M107: =CONCATENATE(TEXT(A107,"0"),"-",TEXT(C107,"0"),"-",TEXT(E107,"0"),"-",TEXT(LEFT(G107,2),"00"),"-",TEXT(RIGHT(G107,1),"0"),TEXT(I107,"0"),"-",TEXT(K107,"00")) -> 1-1-2-12-60-00 | N107: =IF(L107="",IF(J107="",IF(H107="",IF(F107="",IF(D107="",B107,D107),F107),H107),J107),L107) -> FONDOS EN AVANCE | O107: =IF(P107="",0,IF(M106=M107,IF(O106="",0,O106)+1,"")) -> 8 | P107: SUMAT 2018 | Q107: =CONCATENATE(TEXT(A107,"0"),"-",TEXT(C107,"0"),"-",TEXT(E107,"0"),"-",TEXT(LEFT(G107,2),"00"),"-",TEXT(RIGHT(G107,1),"0"),TEXT(I107,"0"),"-",TEXT(K107,"00"),"-",TEXT(O107,"000")) -> 1-1-2-12-60-00-008 | R107: =IF(P107="",IF(L107="",IF(J107="",IF(H107="",IF(F107="",IF(D107="",B107,D107),F107),H107),J107),L107),P107) -> SUMAT 2018
A108: 1 | B108: =VLOOKUP(A108,'ACTIVOS CODIGO'!A:B,2,0) -> ACTIVO | C108: 1 | D108: =VLOOKUP(C108,'ACTIVOS CODIGO'!C:D,2,0) -> ACTIVO DEL TESORO = ACTIVO CORRIENTE | E108: 2 | F108: =VLOOKUP(E108,'ACTIVOS CODIGO'!E:F,2,0) -> ACTIVO EXIGIBLE | G108: 126 | H108: =VLOOKUP(G108,'PUB 21'!$A$1:$B$29,2,0) -> FONDOS EN AVANCE | M108: =CONCATENATE(TEXT(A108,"0"),"-",TEXT(C108,"0"),"-",TEXT(E108,"0"),"-",TEXT(LEFT(G108,2),"00"),"-",TEXT(RIGHT(G108,1),"0"),TEXT(I108,"0"),"-",TEXT(K108,"00")) -> 1-1-2-12-60-00 | N108: =IF(L108="",IF(J108="",IF(H108="",IF(F108="",IF(D108="",B108,D108),F108),H108),J108),L108) -> FONDOS EN AVANCE | O108: =IF(P108="",0,IF(M107=M108,IF(O107="",0,O107)+1,"")) -> 9 | P108: CAMARA MUNICIPAL 2018 | Q108: =CONCATENATE(TEXT(A108,"0"),"-",TEXT(C108,"0"),"-",TEXT(E108,"0"),"-",TEXT(LEFT(G108,2),"00"),"-",TEXT(RIGHT(G108,1),"0"),TEXT(I108,"0"),"-",TEXT(K108,"00"),"-",TEXT(O108,"000")) -> 1-1-2-12-60-00-009 | R108: =IF(P108="",IF(L108="",IF(J108="",IF(H108="",IF(F108="",IF(D108="",B108,D108),F108),H108),J108),L108),P108) -> CAMARA MUNICIPAL 2018
A109: 1 | B109: =VLOOKUP(A109,'ACTIVOS CODIGO'!A:B,2,0) -> ACTIVO | C109: 1 | D109: =VLOOKUP(C109,'ACTIVOS CODIGO'!C:D,2,0) -> ACTIVO DEL TESORO = ACTIVO CORRIENTE | E109: 2 | F109: =VLOOKUP(E109,'ACTIVOS CODIGO'!E:F,2,0) -> ACTIVO EXIGIBLE | G109: 126 | H109: =VLOOKUP(G109,'PUB 21'!$A$1:$B$29,2,0) -> FONDOS EN AVANCE | M109: =CONCATENATE(TEXT(A109,"0"),"-",TEXT(C109,"0"),"-",TEXT(E109,"0"),"-",TEXT(LEFT(G109,2),"00"),"-",TEXT(RIGHT(G109,1),"0"),TEXT(I109,"0"),"-",TEXT(K109,"00")) -> 1-1-2-12-60-00 | N109: =IF(L109="",IF(J109="",IF(H109="",IF(F109="",IF(D109="",B109,D109),F109),H109),J109),L109) -> FONDOS EN AVANCE | O109: =IF(P109="",0,IF(M108=M109,IF(O108="",0,O108)+1,"")) -> 10 | P109: FONDOS EN AVANCE 2019 | Q109: =CONCATENATE(TEXT(A109,"0"),"-",TEXT(C109,"0"),"-",TEXT(E109,"0"),"-",TEXT(LEFT(G109,2),"00"),"-",TEXT(RIGHT(G109,1),"0"),TEXT(I109,"0"),"-",TEXT(K109,"00"),"-",TEXT(O109,"000")) -> 1-1-2-12-60-00-010 | R109: =IF(P109="",IF(L109="",IF(J109="",IF(H109="",IF(F109="",IF(D109="",B109,D109),F109),H109),J109),L109),P109) -> FONDOS EN AVANCE 2019
A110: 1 | B110: =VLOOKUP(A110,'ACTIVOS CODIGO'!A:B,2,0) -> ACTIVO | C110: 1 | D110: =VLOOKUP(C110,'ACTIVOS CODIGO'!C:D,2,0) -> ACTIVO DEL TESORO = ACTIVO CORRIENTE | E110: 2 | F110: =VLOOKUP(E110,'ACTIVOS CODIGO'!E:F,2,0) -> ACTIVO EXIGIBLE | G110: 126 | H110: =VLOOKUP(G110,'PUB 21'!$A$1:$B$29,2,0) -> FONDOS EN AVANCE | M110: =CONCATENATE(TEXT(A110,"0"),"-",TEXT(C110,"0"),"-",TEXT(E110,"0"),"-",TEXT(LEFT(G110,2),"00"),"-",TEXT(RIGHT(G110,1),"0"),TEXT(I110,"0"),"-",TEXT(K110,"00")) -> 1-1-2-12-60-00 | N110: =IF(L110="",IF(J110="",IF(H110="",IF(F110="",IF(D110="",B110,D110),F110),H110),J110),L110) -> FONDOS EN AVANCE | O110: =IF(P110="",0,IF(M109=M110,IF(O109="",0,O109)+1,"")) -> 11 | P110: SINDICATURA MUNICIPAL 2019 | Q110: =CONCATENATE(TEXT(A110,"0"),"-",TEXT(C110,"0"),"-",TEXT(E110,"0"),"-",TEXT(LEFT(G110,2),"00"),"-",TEXT(RIGHT(G110,1),"0"),TEXT(I110,"0"),"-",TEXT(K110,"00"),"-",TEXT(O110,"000")) -> 1-1-2-12-60-00-011 | R110: =IF(P110="",IF(L110="",IF(J110="",IF(H110="",IF(F110="",IF(D110="",B110,D110),F110),H110),J110),L110),P110) -> SINDICATURA MUNICIPAL 2019
A111: 1 | B111: =VLOOKUP(A111,'ACTIVOS CODIGO'!A:B,2,0) -> ACTIVO | C111: 1 | D111: =VLOOKUP(C111,'ACTIVOS CODIGO'!C:D,2,0) -> ACTIVO DEL TESORO = ACTIVO CORRIENTE | E111: 2 | F111: =VLOOKUP(E111,'ACTIVOS CODIGO'!E:F,2,0) -> ACTIVO EXIGIBLE | G111: 126 | H111: =VLOOKUP(G111,'PUB 21'!$A$1:$B$29,2,0) -> FONDOS EN AVANCE | M111: =CONCATENATE(TEXT(A111,"0"),"-",TEXT(C111,"0"),"-",TEXT(E111,"0"),"-",TEXT(LEFT(G111,2),"00"),"-",TEXT(RIGHT(G111,1),"0"),TEXT(I111,"0"),"-",TEXT(K111,"00")) -> 1-1-2-12-60-00 | N111: =IF(L111="",IF(J111="",IF(H111="",IF(F111="",IF(D111="",B111,D111),F111),H111),J111),L111) -> FONDOS EN AVANCE | O111: =IF(P111="",0,IF(M110=M111,IF(O110="",0,O110)+1,"")) -> 12 | P111: DIRECCION DE RECURSOS HUMANOS 2019 | Q111: =CONCATENATE(TEXT(A111,"0"),"-",TEXT(C111,"0"),"-",TEXT(E111,"0"),"-",TEXT(LEFT(G111,2),"00"),"-",TEXT(RIGHT(G111,1),"0"),TEXT(I111,"0"),"-",TEXT(K111,"00"),"-",TEXT(O111,"000")) -> 1-1-2-12-60-00-012 | R111: =IF(P111="",IF(L111="",IF(J111="",IF(H111="",IF(F111="",IF(D111="",B111,D111),F111),H111),J111),L111),P111) -> DIRECCION DE RECURSOS HUMANOS 2019
... A127: 1 | B127: =VLOOKUP(A127,'ACTIVOS CODIGO'!A:B,2,0) -> ACTIVO | C127: 1 | D127: =VLOOKUP(C127,'ACTIVOS CODIGO'!C:D,2,0) -> ACTIVO DEL TESORO = ACTIVO CORRIENTE | E127: 2 | F127: =VLOOKUP(E127,'ACTIVOS CODIGO'!E:F,2,0) -> ACTIVO EXIGIBLE | G127: 126 | H127: =VLOOKUP(G127,'PUB 21'!$A$1:$B$29,2,0) -> FONDOS EN AVANCE | M127: =CONCATENATE(TEXT(A127,"0"),"-",TEXT(C127,"0"),"-",TEXT(E127,"0"),"-",TEXT(LEFT(G127,2),"00"),"-",TEXT(RIGHT(G127,1),"0"),TEXT(I127,"0"),"-",TEXT(K127,"00")) -> 1-1-2-12-60-00 | N127: =IF(L127="",IF(J127="",IF(H127="",IF(F127="",IF(D127="",B127,D127),F127),H127),J127),L127) -> FONDOS EN AVANCE | O127: =IF(P127="",0,IF(M126=M127,IF(O126="",0,O126)+1,"")) -> 28 | P127: CAMARA MUNICIPAL 2022 | Q127: =CONCATENATE(TEXT(A127,"0"),"-",TEXT(C127,"0"),"-",TEXT(E127,"0"),"-",TEXT(LEFT(G127,2),"00"),"-",TEXT(RIGHT(G127,1),"0"),TEXT(I127,"0"),"-",TEXT(K127,"00"),"-",TEXT(O127,"000")) -> 1-1-2-12-60-00-028 | R127: =IF(P127="",IF(L127="",IF(J127="",IF(H127="",IF(F127="",IF(D127="",B127,D127),F127),H127),J127),L127),P127) -> CAMARA MUNICIPAL 2022
A128: 1 | B128: =VLOOKUP(A128,'ACTIVOS CODIGO'!A:B,2,0) -> ACTIVO | C128: 1 | D128: =VLOOKUP(C128,'ACTIVOS CODIGO'!C:D,2,0) -> ACTIVO DEL TESORO = ACTIVO CORRIENTE | E128: 2 | F128: =VLOOKUP(E128,'ACTIVOS CODIGO'!E:F,2,0) -> ACTIVO EXIGIBLE | G128: 128 | H128: =VLOOKUP(G128,'PUB 21'!$A$1:$B$29,2,0) -> FONDOS ANTICIPADOS | M128: =CONCATENATE(TEXT(A128,"0"),"-",TEXT(C128,"0"),"-",TEXT(E128,"0"),"-",TEXT(LEFT(G128,2),"00"),"-",TEXT(RIGHT(G128,1),"0"),TEXT(I128,"0"),"-",TEXT(K128,"00")) -> 1-1-2-12-80-00 | N128: =IF(L128="",IF(J128="",IF(H128="",IF(F128="",IF(D128="",B128,D128),F128),H128),J128),L128) -> FONDOS ANTICIPADOS | O128: =IF(P128="",0,IF(M127=M128,IF(O127="",0,O127)+1,"")) -> 0 | Q128: =CONCATENATE(TEXT(A128,"0"),"-",TEXT(C128,"0"),"-",TEXT(E128,"0"),"-",TEXT(LEFT(G128,2),"00"),"-",TEXT(RIGHT(G128,1),"0"),TEXT(I128,"0"),"-",TEXT(K128,"00"),"-",TEXT(O128,"000")) -> 1-1-2-12-80-00-000 | R128: =IF(P128="",IF(L128="",IF(J128="",IF(H128="",IF(F128="",IF(D128="",B128,D128),F128),H128),J128),L128),P128) -> FONDOS ANTICIPADOS
A129: 1 | B129: =VLOOKUP(A129,'ACTIVOS CODIGO'!A:B,2,0) -> ACTIVO | C129: 1 | D129: =VLOOKUP(C129,'ACTIVOS CODIGO'!C:D,2,0) -> ACTIVO DEL TESORO = ACTIVO CORRIENTE | E129: 2 | F129: =VLOOKUP(E129,'ACTIVOS CODIGO'!E:F,2,0) -> ACTIVO EXIGIBLE | G129: 128 | H129: =VLOOKUP(G129,'PUB 21'!$A$1:$B$29,2,0) -> FONDOS ANTICIPADOS | M129: =CONCATENATE(TEXT(A129,"0"),"-",TEXT(C129,"0"),"-",TEXT(E129,"0"),"-",TEXT(LEFT(G129,2),"00"),"-",TEXT(RIGHT(G129,1),"0"),TEXT(I129,"0"),"-",TEXT(K129,"00")) -> 1-1-2-12-80-00 | N129: =IF(L129="",IF(J129="",IF(H129="",IF(F129="",IF(D129="",B129,D129),F129),H129),J129),L129) -> FONDOS ANTICIPADOS | O129: =IF(P129="",0,IF(M128=M129,IF(O128="",0,O128)+1,"")) -> 1 | P129: ANTICIPOS A CONTRATISTAS 2006 | Q129: =CONCATENATE(TEXT(A129,"0"),"-",TEXT(C129,"0"),"-",TEXT(E129,"0"),"-",TEXT(LEFT(G129,2),"00"),"-",TEXT(RIGHT(G129,1),"0"),TEXT(I129,"0"),"-",TEXT(K129,"00"),"-",TEXT(O129,"000")) -> 1-1-2-12-80-00-001 | R129: =IF(P129="",IF(L129="",IF(J129="",IF(H129="",IF(F129="",IF(D129="",B129,D129),F129),H129),J129),L129),P129) -> ANTICIPOS A CONTRATISTAS 2006
A130: 1 | B130: =VLOOKUP(A130,'ACTIVOS CODIGO'!A:B,2,0) -> ACTIVO | C130: 1 | D130: =VLOOKUP(C130,'ACTIVOS CODIGO'!C:D,2,0) -> ACTIVO DEL TESORO = ACTIVO CORRIENTE | E130: 2 | F130: =VLOOKUP(E130,'ACTIVOS CODIGO'!E:F,2,0) -> ACTIVO EXIGIBLE | G130: 128 | H130: =VLOOKUP(G130,'PUB 21'!$A$1:$B$29,2,0) -> FONDOS ANTICIPADOS | M130: =CONCATENATE(TEXT(A130,"0"),"-",TEXT(C130,"0"),"-",TEXT(E130,"0"),"-",TEXT(LEFT(G130,2),"00"),"-",TEXT(RIGHT(G130,1),"0"),TEXT(I130,"0"),"-",TEXT(K130,"00")) -> 1-1-2-12-80-00 | N130: =IF(L130="",IF(J130="",IF(H130="",IF(F130="",IF(D130="",B130,D130),F130),H130),J130),L130) -> FONDOS ANTICIPADOS | O130: =IF(P130="",0,IF(M129=M130,IF(O129="",0,O129)+1,"")) -> 2 | P130: ANTICIPOS A CONTRATISTAS 2007 | Q130: =CONCATENATE(TEXT(A130,"0"),"-",TEXT(C130,"0"),"-",TEXT(E130,"0"),"-",TEXT(LEFT(G130,2),"00"),"-",TEXT(RIGHT(G130,1),"0"),TEXT(I130,"0"),"-",TEXT(K130,"00"),"-",TEXT(O130,"000")) -> 1-1-2-12-80-00-002 | R130: =IF(P130="",IF(L130="",IF(J130="",IF(H130="",IF(F130="",IF(D130="",B130,D130),F130),H130),J130),L130),P130) -> ANTICIPOS A CONTRATISTAS 2007
A131: 1 | B131: =VLOOKUP(A131,'ACTIVOS CODIGO'!A:B,2,0) -> ACTIVO | C131: 1 | D131: =VLOOKUP(C131,'ACTIVOS CODIGO'!C:D,2,0) -> ACTIVO DEL TESORO = ACTIVO CORRIENTE | E131: 2 | F131: =VLOOKUP(E131,'ACTIVOS CODIGO'!E:F,2,0) -> ACTIVO EXIGIBLE | G131: 128 | H131: =VLOOKUP(G131,'PUB 21'!$A$1:$B$29,2,0) -> FONDOS ANTICIPADOS | M131: =CONCATENATE(TEXT(A131,"0"),"-",TEXT(C131,"0"),"-",TEXT(E131,"0"),"-",TEXT(LEFT(G131,2),"00"),"-",TEXT(RIGHT(G131,1),"0"),TEXT(I131,"0"),"-",TEXT(K131,"00")) -> 1-1-2-12-80-00 | N131: =IF(L131="",IF(J131="",IF(H131="",IF(F131="",IF(D131="",B131,D131),F131),H131),J131),L131) -> FONDOS ANTICIPADOS | O131: =IF(P131="",0,IF(M130=M131,IF(O130="",0,O130)+1,"")) -> 3 | P131: ANTICIPOS A CONTRATISTAS 2008 | Q131: =CONCATENATE(TEXT(A131,"0"),"-",TEXT(C131,"0"),"-",TEXT(E131,"0"),"-",TEXT(LEFT(G131,2),"00"),"-",TEXT(RIGHT(G131,1),"0"),TEXT(I131,"0"),"-",TEXT(K131,"00"),"-",TEXT(O131,"000")) -> 1-1-2-12-80-00-003 | R131: =IF(P131="",IF(L131="",IF(J131="",IF(H131="",IF(F131="",IF(D131="",B131,D131),F131),H131),J131),L131),P131) -> ANTICIPOS A CONTRATISTAS 2008
A132: 1 | B132: =VLOOKUP(A132,'ACTIVOS CODIGO'!A:B,2,0) -> ACTIVO | C132: 1 | D132: =VLOOKUP(C132,'ACTIVOS CODIGO'!C:D,2,0) -> ACTIVO DEL TESORO = ACTIVO CORRIENTE | E132: 2 | F132: =VLOOKUP(E132,'ACTIVOS CODIGO'!E:F,2,0) -> ACTIVO EXIGIBLE | G132: 128 | H132: =VLOOKUP(G132,'PUB 21'!$A$1:$B$29,2,0) -> FONDOS ANTICIPADOS | M132: =CONCATENATE(TEXT(A132,"0"),"-",TEXT(C132,"0"),"-",TEXT(E132,"0"),"-",TEXT(LEFT(G132,2),"00"),"-",TEXT(RIGHT(G132,1),"0"),TEXT(I132,"0"),"-",TEXT(K132,"00")) -> 1-1-2-12-80-00 | N132: =IF(L132="",IF(J132="",IF(H132="",IF(F132="",IF(D132="",B132,D132),F132),H132),J132),L132) -> FONDOS ANTICIPADOS | O132: =IF(P132="",0,IF(M131=M132,IF(O131="",0,O131)+1,"")) -> 4 | P132: ANTICIPOS A CONTRATISTAS 2009 | Q132: =CONCATENATE(TEXT(A132,"0"),"-",TEXT(C132,"0"),"-",TEXT(E132,"0"),"-",TEXT(LEFT(G132,2),"00"),"-",TEXT(RIGHT(G132,1),"0"),TEXT(I132,"0"),"-",TEXT(K132,"00"),"-",TEXT(O132,"000")) -> 1-1-2-12-80-00-004 | R132: =IF(P132="",IF(L132="",IF(J132="",IF(H132="",IF(F132="",IF(D132="",B132,D132),F132),H132),J132),L132),P132) -> ANTICIPOS A CONTRATISTAS 2009
A133: 1 | B133: =VLOOKUP(A133,'ACTIVOS CODIGO'!A:B,2,0) -> ACTIVO | C133: 1 | D133: =VLOOKUP(C133,'ACTIVOS CODIGO'!C:D,2,0) -> ACTIVO DEL TESORO = ACTIVO CORRIENTE | E133: 2 | F133: =VLOOKUP(E133,'ACTIVOS CODIGO'!E:F,2,0) -> ACTIVO EXIGIBLE | G133: 128 | H133: =VLOOKUP(G133,'PUB 21'!$A$1:$B$29,2,0) -> FONDOS ANTICIPADOS | M133: =CONCATENATE(TEXT(A133,"0"),"-",TEXT(C133,"0"),"-",TEXT(E133,"0"),"-",TEXT(LEFT(G133,2),"00"),"-",TEXT(RIGHT(G133,1),"0"),TEXT(I133,"0"),"-",TEXT(K133,"00")) -> 1-1-2-12-80-00 | N133: =IF(L133="",IF(J133="",IF(H133="",IF(F133="",IF(D133="",B133,D133),F133),H133),J133),L133) -> FONDOS ANTICIPADOS | O133: =IF(P133="",0,IF(M132=M133,IF(O132="",0,O132)+1,"")) -> 5 | P133: ANTICIPOS A CONTRATISTAS 2010 | Q133: =CONCATENATE(TEXT(A133,"0"),"-",TEXT(C133,"0"),"-",TEXT(E133,"0"),"-",TEXT(LEFT(G133,2),"00"),"-",TEXT(RIGHT(G133,1),"0"),TEXT(I133,"0"),"-",TEXT(K133,"00"),"-",TEXT(O133,"000")) -> 1-1-2-12-80-00-005 | R133: =IF(P133="",IF(L133="",IF(J133="",IF(H133="",IF(F133="",IF(D133="",B133,D133),F133),H133),J133),L133),P133) -> ANTICIPOS A CONTRATISTAS 2010
A134: 1 | B134: =VLOOKUP(A134,'ACTIVOS CODIGO'!A:B,2,0) -> ACTIVO | C134: 1 | D134: =VLOOKUP(C134,'ACTIVOS CODIGO'!C:D,2,0) -> ACTIVO DEL TESORO = ACTIVO CORRIENTE | E134: 2 | F134: =VLOOKUP(E134,'ACTIVOS CODIGO'!E:F,2,0) -> ACTIVO EXIGIBLE | G134: 128 | H134: =VLOOKUP(G134,'PUB 21'!$A$1:$B$29,2,0) -> FONDOS ANTICIPADOS | M134: =CONCATENATE(TEXT(A134,"0"),"-",TEXT(C134,"0"),"-",TEXT(E134,"0"),"-",TEXT(LEFT(G134,2),"00"),"-",TEXT(RIGHT(G134,1),"0"),TEXT(I134,"0"),"-",TEXT(K134,"00")) -> 1-1-2-12-80-00 | N134: =IF(L134="",IF(J134="",IF(H134="",IF(F134="",IF(D134="",B134,D134),F134),H134),J134),L134) -> FONDOS ANTICIPADOS | O134: =IF(P134="",0,IF(M133=M134,IF(O133="",0,O133)+1,"")) -> 6 | P134: ANTICIPOS A CONTRATISTAS 2011 | Q134: =CONCATENATE(TEXT(A134,"0"),"-",TEXT(C134,"0"),"-",TEXT(E134,"0"),"-",TEXT(LEFT(G134,2),"00"),"-",TEXT(RIGHT(G134,1),"0"),TEXT(I134,"0"),"-",TEXT(K134,"00"),"-",TEXT(O134,"000")) -> 1-1-2-12-80-00-006 | R134: =IF(P134="",IF(L134="",IF(J134="",IF(H134="",IF(F134="",IF(D134="",B134,D134),F134),H134),J134),L134),P134) -> ANTICIPOS A CONTRATISTAS 2011
A135: 1 | B135: =VLOOKUP(A135,'ACTIVOS CODIGO'!A:B,2,0) -> ACTIVO | C135: 1 | D135: =VLOOKUP(C135,'ACTIVOS CODIGO'!C:D,2,0) -> ACTIVO DEL TESORO = ACTIVO CORRIENTE | E135: 2 | F135: =VLOOKUP(E135,'ACTIVOS CODIGO'!E:F,2,0) -> ACTIVO EXIGIBLE | G135: 128 | H135: =VLOOKUP(G135,'PUB 21'!$A$1:$B$29,2,0) -> FONDOS ANTICIPADOS | M135: =CONCATENATE(TEXT(A135,"0"),"-",TEXT(C135,"0"),"-",TEXT(E135,"0"),"-",TEXT(LEFT(G135,2),"00"),"-",TEXT(RIGHT(G135,1),"0"),TEXT(I135,"0"),"-",TEXT(K135,"00")) -> 1-1-2-12-80-00 | N135: =IF(L135="",IF(J135="",IF(H135="",IF(F135="",IF(D135="",B135,D135),F135),H135),J135),L135) -> FONDOS ANTICIPADOS | O135: =IF(P135="",0,IF(M134=M135,IF(O134="",0,O134)+1,"")) -> 7 | P135: ANTICIPOS A CONTRATISTAS 2015 | Q135: =CONCATENATE(TEXT(A135,"0"),"-",TEXT(C135,"0"),"-",TEXT(E135,"0"),"-",TEXT(LEFT(G135,2),"00"),"-",TEXT(RIGHT(G135,1),"0"),TEXT(I135,"0"),"-",TEXT(K135,"00"),"-",TEXT(O135,"000")) -> 1-1-2-12-80-00-007 | R135: =IF(P135="",IF(L135="",IF(J135="",IF(H135="",IF(F135="",IF(D135="",B135,D135),F135),H135),J135),L135),P135) -> ANTICIPOS A CONTRATISTAS 2015
A136: 1 | B136: =VLOOKUP(A136,'ACTIVOS CODIGO'!A:B,2,0) -> ACTIVO | C136: 1 | D136: =VLOOKUP(C136,'ACTIVOS CODIGO'!C:D,2,0) -> ACTIVO DEL TESORO = ACTIVO CORRIENTE | E136: 2 | F136: =VLOOKUP(E136,'ACTIVOS CODIGO'!E:F,2,0) -> ACTIVO EXIGIBLE | G136: 128 | H136: =VLOOKUP(G136,'PUB 21'!$A$1:$B$29,2,0) -> FONDOS ANTICIPADOS | M136: =CONCATENATE(TEXT(A136,"0"),"-",TEXT(C136,"0"),"-",TEXT(E136,"0"),"-",TEXT(LEFT(G136,2),"00"),"-",TEXT(RIGHT(G136,1),"0"),TEXT(I136,"0"),"-",TEXT(K136,"00")) -> 1-1-2-12-80-00 | N136: =IF(L136="",IF(J136="",IF(H136="",IF(F136="",IF(D136="",B136,D136),F136),H136),J136),L136) -> FONDOS ANTICIPADOS | O136: =IF(P136="",0,IF(M135=M136,IF(O135="",0,O135)+1,"")) -> 8 | P136: ANTICIPOS A CONTRATISTAS 2014 | Q136: =CONCATENATE(TEXT(A136,"0"),"-",TEXT(C136,"0"),"-",TEXT(E136,"0"),"-",TEXT(LEFT(G136,2),"00"),"-",TEXT(RIGHT(G136,1),"0"),TEXT(I136,"0"),"-",TEXT(K136,"00"),"-",TEXT(O136,"000")) -> 1-1-2-12-80-00-008 | R136: =IF(P136="",IF(L136="",IF(J136="",IF(H136="",IF(F136="",IF(D136="",B136,D136),F136),H136),J136),L136),P136) -> ANTICIPOS A CONTRATISTAS 2014
A137: 1 | B137: =VLOOKUP(A137,'ACTIVOS CODIGO'!A:B,2,0) -> ACTIVO | C137: 1 | D137: =VLOOKUP(C137,'ACTIVOS CODIGO'!C:D,2,0) -> ACTIVO DEL TESORO = ACTIVO CORRIENTE | E137: 2 | F137: =VLOOKUP(E137,'ACTIVOS CODIGO'!E:F,2,0) -> ACTIVO EXIGIBLE | G137: 128 | H137: =VLOOKUP(G137,'PUB 21'!$A$1:$B$29,2,0) -> FONDOS ANTICIPADOS | M137: =CONCATENATE(TEXT(A137,"0"),"-",TEXT(C137,"0"),"-",TEXT(E137,"0"),"-",TEXT(LEFT(G137,2),"00"),"-",TEXT(RIGHT(G137,1),"0"),TEXT(I137,"0"),"-",TEXT(K137,"00")) -> 1-1-2-12-80-00 | N137: =IF(L137="",IF(J137="",IF(H137="",IF(F137="",IF(D137="",B137,D137),F137),H137),J137),L137) -> FONDOS ANTICIPADOS | O137: =IF(P137="",0,IF(M136=M137,IF(O136="",0,O136)+1,"")) -> 9 | P137: ANTICIPOS A CONTRATISTAS 2016 | Q137: =CONCATENATE(TEXT(A137,"0"),"-",TEXT(C137,"0"),"-",TEXT(E137,"0"),"-",TEXT(LEFT(G137,2),"00"),"-",TEXT(RIGHT(G137,1),"0"),TEXT(I137,"0"),"-",TEXT(K137,"00"),"-",TEXT(O137,"000")) -> 1-1-2-12-80-00-009 | R137: =IF(P137="",IF(L137="",IF(J137="",IF(H137="",IF(F137="",IF(D137="",B137,D137),F137),H137),J137),L137),P137) -> ANTICIPOS A CONTRATISTAS 2016
A138: 1 | B138: =VLOOKUP(A138,'ACTIVOS CODIGO'!A:B,2,0) -> ACTIVO | C138: 1 | D138: =VLOOKUP(C138,'ACTIVOS CODIGO'!C:D,2,0) -> ACTIVO DEL TESORO = ACTIVO CORRIENTE | E138: 2 | F138: =VLOOKUP(E138,'ACTIVOS CODIGO'!E:F,2,0) -> ACTIVO EXIGIBLE | G138: 128 | H138: =VLOOKUP(G138,'PUB 21'!$A$1:$B$29,2,0) -> FONDOS ANTICIPADOS | M138: =CONCATENATE(TEXT(A138,"0"),"-",TEXT(C138,"0"),"-",TEXT(E138,"0"),"-",TEXT(LEFT(G138,2),"00"),"-",TEXT(RIGHT(G138,1),"0"),TEXT(I138,"0"),"-",TEXT(K138,"00")) -> 1-1-2-12-80-00 | N138: =IF(L138="",IF(J138="",IF(H138="",IF(F138="",IF(D138="",B138,D138),F138),H138),J138),L138) -> FONDOS ANTICIPADOS | O138: =IF(P138="",0,IF(M137=M138,IF(O137="",0,O137)+1,"")) -> 10 | P138: ANTICIPOS A CONTRATISTAS 2018 | Q138: =CONCATENATE(TEXT(A138,"0"),"-",TEXT(C138,"0"),"-",TEXT(E138,"0"),"-",TEXT(LEFT(G138,2),"00"),"-",TEXT(RIGHT(G138,1),"0"),TEXT(I138,"0"),"-",TEXT(K138,"00"),"-",TEXT(O138,"000")) -> 1-1-2-12-80-00-010 | R138: =IF(P138="",IF(L138="",IF(J138="",IF(H138="",IF(F138="",IF(D138="",B138,D138),F138),H138),J138),L138),P138) -> ANTICIPOS A CONTRATISTAS 2018
A139: 1 | B139: =VLOOKUP(A139,'ACTIVOS CODIGO'!A:B,2,0) -> ACTIVO | C139: 1 | D139: =VLOOKUP(C139,'ACTIVOS CODIGO'!C:D,2,0) -> ACTIVO DEL TESORO = ACTIVO CORRIENTE | E139: 2 | F139: =VLOOKUP(E139,'ACTIVOS CODIGO'!E:F,2,0) -> ACTIVO EXIGIBLE | G139: 128 | H139: =VLOOKUP(G139,'PUB 21'!$A$1:$B$29,2,0) -> FONDOS ANTICIPADOS | M139: =CONCATENATE(TEXT(A139,"0"),"-",TEXT(C139,"0"),"-",TEXT(E139,"0"),"-",TEXT(LEFT(G139,2),"00"),"-",TEXT(RIGHT(G139,1),"0"),TEXT(I139,"0"),"-",TEXT(K139,"00")) -> 1-1-2-12-80-00 | N139: =IF(L139="",IF(J139="",IF(H139="",IF(F139="",IF(D139="",B139,D139),F139),H139),J139),L139) -> FONDOS ANTICIPADOS | O139: =IF(P139="",0,IF(M138=M139,IF(O138="",0,O138)+1,"")) -> 11 | P139: ANTICIPOS A CONTRATISTAS 2017 | Q139: =CONCATENATE(TEXT(A139,"0"),"-",TEXT(C139,"0"),"-",TEXT(E139,"0"),"-",TEXT(LEFT(G139,2),"00"),"-",TEXT(RIGHT(G139,1),"0"),TEXT(I139,"0"),"-",TEXT(K139,"00"),"-",TEXT(O139,"000")) -> 1-1-2-12-80-00-011 | R139: =IF(P139="",IF(L139="",IF(J139="",IF(H139="",IF(F139="",IF(D139="",B139,D139),F139),H139),J139),L139),P139) -> ANTICIPOS A CONTRATISTAS 2017
A140: 1 | B140: =VLOOKUP(A140,'ACTIVOS CODIGO'!A:B,2,0) -> ACTIVO | C140: 1 | D140: =VLOOKUP(C140,'ACTIVOS CODIGO'!C:D,2,0) -> ACTIVO DEL TESORO = ACTIVO CORRIENTE | E140: 2 | F140: =VLOOKUP(E140,'ACTIVOS CODIGO'!E:F,2,0) -> ACTIVO EXIGIBLE | G140: 130 | H140: =VLOOKUP(G140,'PUB 21'!$A$1:$B$29,2,0) -> FONDOS ESPECIALES | M140: =CONCATENATE(TEXT(A140,"0"),"-",TEXT(C140,"0"),"-",TEXT(E140,"0"),"-",TEXT(LEFT(G140,2),"00"),"-",TEXT(RIGHT(G140,1),"0"),TEXT(I140,"0"),"-",TEXT(K140,"00")) -> 1-1-2-13-00-00 | N140: =IF(L140="",IF(J140="",IF(H140="",IF(F140="",IF(D140="",B140,D140),F140),H140),J140),L140) -> FONDOS ESPECIALES | O140: =IF(P140="",0,IF(M139=M140,IF(O139="",0,O139)+1,"")) -> 0 | Q140: =CONCATENATE(TEXT(A140,"0"),"-",TEXT(C140,"0"),"-",TEXT(E140,"0"),"-",TEXT(LEFT(G140,2),"00"),"-",TEXT(RIGHT(G140,1),"0"),TEXT(I140,"0"),"-",TEXT(K140,"00"),"-",TEXT(O140,"000")) -> 1-1-2-13-00-00-000 | R140: =IF(P140="",IF(L140="",IF(J140="",IF(H140="",IF(F140="",IF(D140="",B140,D140),F140),H140),J140),L140),P140) -> FONDOS ESPECIALES
A141: 1 | B141: =VLOOKUP(A141,'ACTIVOS CODIGO'!A:B,2,0) -> ACTIVO | C141: 1 | D141: =VLOOKUP(C141,'ACTIVOS CODIGO'!C:D,2,0) -> ACTIVO DEL TESORO = ACTIVO CORRIENTE | E141: 2 | F141: =VLOOKUP(E141,'ACTIVOS CODIGO'!E:F,2,0) -> ACTIVO EXIGIBLE | G141: 132 | H141: =VLOOKUP(G141,'PUB 21'!$A$1:$B$29,2,0) -> FONDOS DE TERCEROS | M141: =CONCATENATE(TEXT(A141,"0"),"-",TEXT(C141,"0"),"-",TEXT(E141,"0"),"-",TEXT(LEFT(G141,2),"00"),"-",TEXT(RIGHT(G141,1),"0"),TEXT(I141,"0"),"-",TEXT(K141,"00")) -> 1-1-2-13-20-00 | N141: =IF(L141="",IF(J141="",IF(H141="",IF(F141="",IF(D141="",B141,D141),F141),H141),J141),L141) -> FONDOS DE TERCEROS | O141: =IF(P141="",0,IF(M140=M141,IF(O140="",0,O140)+1,"")) -> 0 | Q141: =CONCATENATE(TEXT(A141,"0"),"-",TEXT(C141,"0"),"-",TEXT(E141,"0"),"-",TEXT(LEFT(G141,2),"00"),"-",TEXT(RIGHT(G141,1),"0"),TEXT(I141,"0"),"-",TEXT(K141,"00"),"-",TEXT(O141,"000")) -> 1-1-2-13-20-00-000 | R141: =IF(P141="",IF(L141="",IF(J141="",IF(H141="",IF(F141="",IF(D141="",B141,D141),F141),H141),J141),L141),P141) -> FONDOS DE TERCEROS
A142: 1 | B142: =VLOOKUP(A142,'ACTIVOS CODIGO'!A:B,2,0) -> ACTIVO | C142: 1 | D142: =VLOOKUP(C142,'ACTIVOS CODIGO'!C:D,2,0) -> ACTIVO DEL TESORO = ACTIVO CORRIENTE | E142: 2 | F142: =VLOOKUP(E142,'ACTIVOS CODIGO'!E:F,2,0) -> ACTIVO EXIGIBLE | G142: 132 | H142: =VLOOKUP(G142,'PUB 21'!$A$1:$B$29,2,0) -> FONDOS DE TERCEROS | M142: =CONCATENATE(TEXT(A142,"0"),"-",TEXT(C142,"0"),"-",TEXT(E142,"0"),"-",TEXT(LEFT(G142,2),"00"),"-",TEXT(RIGHT(G142,1),"0"),TEXT(I142,"0"),"-",TEXT(K142,"00")) -> 1-1-2-13-20-00 | N142: =IF(L142="",IF(J142="",IF(H142="",IF(F142="",IF(D142="",B142,D142),F142),H142),J142),L142) -> FONDOS DE TERCEROS | O142: =IF(P142="",0,IF(M141=M142,IF(O141="",0,O141)+1,"")) -> 1 | P142: F.T.BANCO DE VENEZUELA 2020 | Q142: =CONCATENATE(TEXT(A142,"0"),"-",TEXT(C142,"0"),"-",TEXT(E142,"0"),"-",TEXT(LEFT(G142,2),"00"),"-",TEXT(RIGHT(G142,1),"0"),TEXT(I142,"0"),"-",TEXT(K142,"00"),"-",TEXT(O142,"000")) -> 1-1-2-13-20-00-001 | R142: =IF(P142="",IF(L142="",IF(J142="",IF(H142="",IF(F142="",IF(D142="",B142,D142),F142),H142),J142),L142),P142) -> F.T.BANCO DE VENEZUELA 2020
A143: 1 | B143: =VLOOKUP(A143,'ACTIVOS CODIGO'!A:B,2,0) -> ACTIVO | C143: 1 | D143: =VLOOKUP(C143,'ACTIVOS CODIGO'!C:D,2,0) -> ACTIVO DEL TESORO = ACTIVO CORRIENTE | E143: 2 | F143: =VLOOKUP(E143,'ACTIVOS CODIGO'!E:F,2,0) -> ACTIVO EXIGIBLE | G143: 132 | H143: =VLOOKUP(G143,'PUB 21'!$A$1:$B$29,2,0) -> FONDOS DE TERCEROS | M143: =CONCATENATE(TEXT(A143,"0"),"-",TEXT(C143,"0"),"-",TEXT(E143,"0"),"-",TEXT(LEFT(G143,2),"00"),"-",TEXT(RIGHT(G143,1),"0"),TEXT(I143,"0"),"-",TEXT(K143,"00")) -> 1-1-2-13-20-00 | N143: =IF(L143="",IF(J143="",IF(H143="",IF(F143="",IF(D143="",B143,D143),F143),H143),J143),L143) -> FONDOS DE TERCEROS | O143: =IF(P143="",0,IF(M142=M143,IF(O142="",0,O142)+1,"")) -> 2 | P143: F.T. BANCO BICENTENARIO 2020 | Q143: =CONCATENATE(TEXT(A143,"0"),"-",TEXT(C143,"0"),"-",TEXT(E143,"0"),"-",TEXT(LEFT(G143,2),"00"),"-",TEXT(RIGHT(G143,1),"0"),TEXT(I143,"0"),"-",TEXT(K143,"00"),"-",TEXT(O143,"000")) -> 1-1-2-13-20-00-002 | R143: =IF(P143="",IF(L143="",IF(J143="",IF(H143="",IF(F143="",IF(D143="",B143,D143),F143),H143),J143),L143),P143) -> F.T. BANCO BICENTENARIO 2020
A144: 1 | B144: =VLOOKUP(A144,'ACTIVOS CODIGO'!A:B,2,0) -> ACTIVO | C144: 1 | D144: =VLOOKUP(C144,'ACTIVOS CODIGO'!C:D,2,0) -> ACTIVO DEL TESORO = ACTIVO CORRIENTE | E144: 2 | F144: =VLOOKUP(E144,'ACTIVOS CODIGO'!E:F,2,0) -> ACTIVO EXIGIBLE | G144: 132 | H144: =VLOOKUP(G144,'PUB 21'!$A$1:$B$29,2,0) -> FONDOS DE TERCEROS | M144: =CONCATENATE(TEXT(A144,"0"),"-",TEXT(C144,"0"),"-",TEXT(E144,"0"),"-",TEXT(LEFT(G144,2),"00"),"-",TEXT(RIGHT(G144,1),"0"),TEXT(I144,"0"),"-",TEXT(K144,"00")) -> 1-1-2-13-20-00 | N144: =IF(L144="",IF(J144="",IF(H144="",IF(F144="",IF(D144="",B144,D144),F144),H144),J144),L144) -> FONDOS DE TERCEROS | O144: =IF(P144="",0,IF(M143=M144,IF(O143="",0,O143)+1,"")) -> 3 | P144: F.T.BANCO DE VENEZUELA 2021 | Q144: =CONCATENATE(TEXT(A144,"0"),"-",TEXT(C144,"0"),"-",TEXT(E144,"0"),"-",TEXT(LEFT(G144,2),"00"),"-",TEXT(RIGHT(G144,1),"0"),TEXT(I144,"0"),"-",TEXT(K144,"00"),"-",TEXT(O144,"000")) -> 1-1-2-13-20-00-003 | R144: =IF(P144="",IF(L144="",IF(J144="",IF(H144="",IF(F144="",IF(D144="",B144,D144),F144),H144),J144),L144),P144) -> F.T.BANCO DE VENEZUELA 2021
A145: 1 | B145: =VLOOKUP(A145,'ACTIVOS CODIGO'!A:B,2,0) -> ACTIVO | C145: 1 | D145: =VLOOKUP(C145,'ACTIVOS CODIGO'!C:D,2,0) -> ACTIVO DEL TESORO = ACTIVO CORRIENTE | E145: 2 | F145: =VLOOKUP(E145,'ACTIVOS CODIGO'!E:F,2,0) -> ACTIVO EXIGIBLE | G145: 132 | H145: =VLOOKUP(G145,'PUB 21'!$A$1:$B$29,2,0) -> FONDOS DE TERCEROS | M145: =CONCATENATE(TEXT(A145,"0"),"-",TEXT(C145,"0"),"-",TEXT(E145,"0"),"-",TEXT(LEFT(G145,2),"00"),"-",TEXT(RIGHT(G145,1),"0"),TEXT(I145,"0"),"-",TEXT(K145,"00")) -> 1-1-2-13-20-00 | N145: =IF(L145="",IF(J145="",IF(H145="",IF(F145="",IF(D145="",B145,D145),F145),H145),J145),L145) -> FONDOS DE TERCEROS | O145: =IF(P145="",0,IF(M144=M145,IF(O144="",0,O144)+1,"")) -> 4 | P145: F.T. BANCO BICENTENARIO 2021 | Q145: =CONCATENATE(TEXT(A145,"0"),"-",TEXT(C145,"0"),"-",TEXT(E145,"0"),"-",TEXT(LEFT(G145,2),"00"),"-",TEXT(RIGHT(G145,1),"0"),TEXT(I145,"0"),"-",TEXT(K145,"00"),"-",TEXT(O145,"000")) -> 1-1-2-13-20-00-004 | R145: =IF(P145="",IF(L145="",IF(J145="",IF(H145="",IF(F145="",IF(D145="",B145,D145),F145),H145),J145),L145),P145) -> F.T. BANCO BICENTENARIO 2021
A146: 1 | B146: =VLOOKUP(A146,'ACTIVOS CODIGO'!A:B,2,0) -> ACTIVO | C146: 2 | D146: =VLOOKUP(C146,'ACTIVOS CODIGO'!C:D,2,0) -> ACTIVO DE LA HACIENDA = ACTIVO NO CORRIENTE | G146: 0 | M146: =CONCATENATE(TEXT(A146,"0"),"-",TEXT(C146,"0"),"-",TEXT(E146,"0"),"-",TEXT(LEFT(G146,2),"00"),"-",TEXT(RIGHT(G146,1),"0"),TEXT(I146,"0"),"-",TEXT(K146,"00")) -> 1-2-0-00-00-00 | N146: =IF(L146="",IF(J146="",IF(H146="",IF(F146="",IF(D146="",B146,D146),F146),H146),J146),L146) -> ACTIVO DE LA HACIENDA = ACTIVO NO CORRIENTE | O146: =IF(P146="",0,IF(M145=M146,IF(O145="",0,O145)+1,"")) -> 0 | Q146: =CONCATENATE(TEXT(A146,"0"),"-",TEXT(C146,"0"),"-",TEXT(E146,"0"),"-",TEXT(LEFT(G146,2),"00"),"-",TEXT(RIGHT(G146,1),"0"),TEXT(I146,"0"),"-",TEXT(K146,"00"),"-",TEXT(O146,"000")) -> 1-2-0-00-00-00-000 | R146: =IF(P146="",IF(L146="",IF(J146="",IF(H146="",IF(F146="",IF(D146="",B146,D146),F146),H146),J146),L146),P146) -> ACTIVO DE LA HACIENDA = ACTIVO NO CORRIENTE
A147: 1 | B147: =VLOOKUP(A147,'ACTIVOS CODIGO'!A:B,2,0) -> ACTIVO | C147: 2 | D147: =VLOOKUP(C147,'ACTIVOS CODIGO'!C:D,2,0) -> ACTIVO DE LA HACIENDA = ACTIVO NO CORRIENTE | E147: 1 | F147: =VLOOKUP(E147,'ACTIVOS CODIGO'!E:F,2,0) -> ACTIVO DISPONIBLE | G147: 0 | M147: =CONCATENATE(TEXT(A147,"0"),"-",TEXT(C147,"0"),"-",TEXT(E147,"0"),"-",TEXT(LEFT(G147,2),"00"),"-",TEXT(RIGHT(G147,1),"0"),TEXT(I147,"0"),"-",TEXT(K147,"00")) -> 1-2-1-00-00-00 | N147: =IF(L147="",IF(J147="",IF(H147="",IF(F147="",IF(D147="",B147,D147),F147),H147),J147),L147) -> ACTIVO DISPONIBLE | O147: =IF(P147="",0,IF(M146=M147,IF(O146="",0,O146)+1,"")) -> 0 | Q147: =CONCATENATE(TEXT(A147,"0"),"-",TEXT(C147,"0"),"-",TEXT(E147,"0"),"-",TEXT(LEFT(G147,2),"00"),"-",TEXT(RIGHT(G147,1),"0"),TEXT(I147,"0"),"-",TEXT(K147,"00"),"-",TEXT(O147,"000")) -> 1-2-1-00-00-00-000 | R147: =IF(P147="",IF(L147="",IF(J147="",IF(H147="",IF(F147="",IF(D147="",B147,D147),F147),H147),J147),L147),P147) -> ACTIVO DISPONIBLE
A148: 1 | B148: =VLOOKUP(A148,'ACTIVOS CODIGO'!A:B,2,0) -> ACTIVO | C148: 2 | D148: =VLOOKUP(C148,'ACTIVOS CODIGO'!C:D,2,0) -> ACTIVO DE LA HACIENDA = ACTIVO NO CORRIENTE | E148: 1 | F148: =VLOOKUP(E148,'ACTIVOS CODIGO'!E:F,2,0) -> ACTIVO DISPONIBLE | G148: 200 | H148: =VLOOKUP(G148,'PUB 21'!$A$1:$B$29,2,0) -> SITUACION FISCAL DEL TESORO | M148: =CONCATENATE(TEXT(A148,"0"),"-",TEXT(C148,"0"),"-",TEXT(E148,"0"),"-",TEXT(LEFT(G148,2),"00"),"-",TEXT(RIGHT(G148,1),"0"),TEXT(I148,"0"),"-",TEXT(K148,"00")) -> 1-2-1-20-00-00 | N148: =IF(L148="",IF(J148="",IF(H148="",IF(F148="",IF(D148="",B148,D148),F148),H148),J148),L148) -> SITUACION FISCAL DEL TESORO | O148: =IF(P148="",0,IF(M147=M148,IF(O147="",0,O147)+1,"")) -> 0 | Q148: =CONCATENATE(TEXT(A148,"0"),"-",TEXT(C148,"0"),"-",TEXT(E148,"0"),"-",TEXT(LEFT(G148,2),"00"),"-",TEXT(RIGHT(G148,1),"0"),TEXT(I148,"0"),"-",TEXT(K148,"00"),"-",TEXT(O148,"000")) -> 1-2-1-20-00-00-000 | R148: =IF(P148="",IF(L148="",IF(J148="",IF(H148="",IF(F148="",IF(D148="",B148,D148),F148),H148),J148),L148),P148) -> SITUACION FISCAL DEL TESORO
A149: 1 | B149: =VLOOKUP(A149,'ACTIVOS CODIGO'!A:B,2,0) -> ACTIVO | C149: 2 | D149: =VLOOKUP(C149,'ACTIVOS CODIGO'!C:D,2,0) -> ACTIVO DE LA HACIENDA = ACTIVO NO CORRIENTE | E149: 1 | F149: =VLOOKUP(E149,'ACTIVOS CODIGO'!E:F,2,0) -> ACTIVO DISPONIBLE | G149: 210 | H149: =VLOOKUP(G149,'PUB 21'!$A$1:$B$29,2,0) -> APORTE DE CAPITAL Y ACCIONES | M149: =CONCATENATE(TEXT(A149,"0"),"-",TEXT(C149,"0"),"-",TEXT(E149,"0"),"-",TEXT(LEFT(G149,2),"00"),"-",TEXT(RIGHT(G149,1),"0"),TEXT(I149,"0"),"-",TEXT(K149,"00")) -> 1-2-1-21-00-00 | N149: =IF(L149="",IF(J149="",IF(H149="",IF(F149="",IF(D149="",B149,D149),F149),H149),J149),L149) -> APORTE DE CAPITAL Y ACCIONES | O149: =IF(P149="",0,IF(M148=M149,IF(O148="",0,O148)+1,"")) -> 0 | Q149: =CONCATENATE(TEXT(A149,"0"),"-",TEXT(C149,"0"),"-",TEXT(E149,"0"),"-",TEXT(LEFT(G149,2),"00"),"-",TEXT(RIGHT(G149,1),"0"),TEXT(I149,"0"),"-",TEXT(K149,"00"),"-",TEXT(O149,"000")) -> 1-2-1-21-00-00-000 | R149: =IF(P149="",IF(L149="",IF(J149="",IF(H149="",IF(F149="",IF(D149="",B149,D149),F149),H149),J149),L149),P149) -> APORTE DE CAPITAL Y ACCIONES
A150: 1 | B150: =VLOOKUP(A150,'ACTIVOS CODIGO'!A:B,2,0) -> ACTIVO | C150: 2 | D150: =VLOOKUP(C150,'ACTIVOS CODIGO'!C:D,2,0) -> ACTIVO DE LA HACIENDA = ACTIVO NO CORRIENTE | E150: 1 | F150: =VLOOKUP(E150,'ACTIVOS CODIGO'!E:F,2,0) -> ACTIVO DISPONIBLE | G150: 210 | H150: =VLOOKUP(G150,'PUB 21'!$A$1:$B$29,2,0) -> APORTE DE CAPITAL Y ACCIONES | K150: 1 | L150: ACCIONES | M150: =CONCATENATE(TEXT(A150,"0"),"-",TEXT(C150,"0"),"-",TEXT(E150,"0"),"-",TEXT(LEFT(G150,2),"00"),"-",TEXT(RIGHT(G150,1),"0"),TEXT(I150,"0"),"-",TEXT(K150,"00")) -> 1-2-1-21-00-01 | N150: =IF(L150="",IF(J150="",IF(H150="",IF(F150="",IF(D150="",B150,D150),F150),H150),J150),L150) -> ACCIONES | O150: =IF(P150="",0,IF(M149=M150,IF(O149="",0,O149)+1,"")) -> 0 | Q150: =CONCATENATE(TEXT(A150,"0"),"-",TEXT(C150,"0"),"-",TEXT(E150,"0"),"-",TEXT(LEFT(G150,2),"00"),"-",TEXT(RIGHT(G150,1),"0"),TEXT(I150,"0"),"-",TEXT(K150,"00"),"-",TEXT(O150,"000")) -> 1-2-1-21-00-01-000 | R150: =IF(P150="",IF(L150="",IF(J150="",IF(H150="",IF(F150="",IF(D150="",B150,D150),F150),H150),J150),L150),P150) -> ACCIONES
A151: 1 | B151: =VLOOKUP(A151,'ACTIVOS CODIGO'!A:B,2,0) -> ACTIVO | C151: 2 | D151: =VLOOKUP(C151,'ACTIVOS CODIGO'!C:D,2,0) -> ACTIVO DE LA HACIENDA = ACTIVO NO CORRIENTE | E151: 1 | F151: =VLOOKUP(E151,'ACTIVOS CODIGO'!E:F,2,0) -> ACTIVO DISPONIBLE | G151: 210 | H151: =VLOOKUP(G151,'PUB 21'!$A$1:$B$29,2,0) -> APORTE DE CAPITAL Y ACCIONES | K151: 1 | L151: ACCIONES | M151: =CONCATENATE(TEXT(A151,"0"),"-",TEXT(C151,"0"),"-",TEXT(E151,"0"),"-",TEXT(LEFT(G151,2),"00"),"-",TEXT(RIGHT(G151,1),"0"),TEXT(I151,"0"),"-",TEXT(K151,"00")) -> 1-2-1-21-00-01 | N151: =IF(L151="",IF(J151="",IF(H151="",IF(F151="",IF(D151="",B151,D151),F151),H151),J151),L151) -> ACCIONES | O151: =IF(P151="",0,IF(M150=M151,IF(O150="",0,O150)+1,"")) -> 1 | P151: ACCIONES Y ACCIONES INMERCA | Q151: =CONCATENATE(TEXT(A151,"0"),"-",TEXT(C151,"0"),"-",TEXT(E151,"0"),"-",TEXT(LEFT(G151,2),"00"),"-",TEXT(RIGHT(G151,1),"0"),TEXT(I151,"0"),"-",TEXT(K151,"00"),"-",TEXT(O151,"000")) -> 1-2-1-21-00-01-001 | R151: =IF(P151="",IF(L151="",IF(J151="",IF(H151="",IF(F151="",IF(D151="",B151,D151),F151),H151),J151),L151),P151) -> ACCIONES Y ACCIONES INMERCA
A152: 1 | B152: =VLOOKUP(A152,'ACTIVOS CODIGO'!A:B,2,0) -> ACTIVO | C152: 2 | D152: =VLOOKUP(C152,'ACTIVOS CODIGO'!C:D,2,0) -> ACTIVO DE LA HACIENDA = ACTIVO NO CORRIENTE | E152: 2 | F152: =VLOOKUP(E152,'ACTIVOS CODIGO'!E:F,2,0) -> ACTIVO EXIGIBLE | G152: 212 | H152: =VLOOKUP(G152,'PUB 21'!$A$1:$B$29,2,0) -> BIENES INMUEBLES | M152: =CONCATENATE(TEXT(A152,"0"),"-",TEXT(C152,"0"),"-",TEXT(E152,"0"),"-",TEXT(LEFT(G152,2),"00"),"-",TEXT(RIGHT(G152,1),"0"),TEXT(I152,"0"),"-",TEXT(K152,"00")) -> 1-2-2-21-20-00 | N152: =IF(L152="",IF(J152="",IF(H152="",IF(F152="",IF(D152="",B152,D152),F152),H152),J152),L152) -> BIENES INMUEBLES | O152: =IF(P152="",0,IF(M151=M152,IF(O151="",0,O151)+1,"")) -> 0 | Q152: =CONCATENATE(TEXT(A152,"0"),"-",TEXT(C152,"0"),"-",TEXT(E152,"0"),"-",TEXT(LEFT(G152,2),"00"),"-",TEXT(RIGHT(G152,1),"0"),TEXT(I152,"0"),"-",TEXT(K152,"00"),"-",TEXT(O152,"000")) -> 1-2-2-21-20-00-000 | R152: =IF(P152="",IF(L152="",IF(J152="",IF(H152="",IF(F152="",IF(D152="",B152,D152),F152),H152),J152),L152),P152) -> BIENES INMUEBLES
A153: 1 | B153: =VLOOKUP(A153,'ACTIVOS CODIGO'!A:B,2,0) -> ACTIVO | C153: 2 | D153: =VLOOKUP(C153,'ACTIVOS CODIGO'!C:D,2,0) -> ACTIVO DE LA HACIENDA = ACTIVO NO CORRIENTE | E153: 2 | F153: =VLOOKUP(E153,'ACTIVOS CODIGO'!E:F,2,0) -> ACTIVO EXIGIBLE | G153: 212 | H153: =VLOOKUP(G153,'PUB 21'!$A$1:$B$29,2,0) -> BIENES INMUEBLES | M153: =CONCATENATE(TEXT(A153,"0"),"-",TEXT(C153,"0"),"-",TEXT(E153,"0"),"-",TEXT(LEFT(G153,2),"00"),"-",TEXT(RIGHT(G153,1),"0"),TEXT(I153,"0"),"-",TEXT(K153,"00")) -> 1-2-2-21-20-00 | N153: =IF(L153="",IF(J153="",IF(H153="",IF(F153="",IF(D153="",B153,D153),F153),H153),J153),L153) -> BIENES INMUEBLES | O153: =IF(P153="",0,IF(M152=M153,IF(O152="",0,O152)+1,"")) -> 1 | P153: PARROQUIA ALTAGRACIA | Q153: =CONCATENATE(TEXT(A153,"0"),"-",TEXT(C153,"0"),"-",TEXT(E153,"0"),"-",TEXT(LEFT(G153,2),"00"),"-",TEXT(RIGHT(G153,1),"0"),TEXT(I153,"0"),"-",TEXT(K153,"00"),"-",TEXT(O153,"000")) -> 1-2-2-21-20-00-001 | R153: =IF(P153="",IF(L153="",IF(J153="",IF(H153="",IF(F153="",IF(D153="",B153,D153),F153),H153),J153),L153),P153) -> PARROQUIA ALTAGRACIA
A154: 1 | B154: =VLOOKUP(A154,'ACTIVOS CODIGO'!A:B,2,0) -> ACTIVO | C154: 2 | D154: =VLOOKUP(C154,'ACTIVOS CODIGO'!C:D,2,0) -> ACTIVO DE LA HACIENDA = ACTIVO NO CORRIENTE | E154: 2 | F154: =VLOOKUP(E154,'ACTIVOS CODIGO'!E:F,2,0) -> ACTIVO EXIGIBLE | G154: 212 | H154: =VLOOKUP(G154,'PUB 21'!$A$1:$B$29,2,0) -> BIENES INMUEBLES | M154: =CONCATENATE(TEXT(A154,"0"),"-",TEXT(C154,"0"),"-",TEXT(E154,"0"),"-",TEXT(LEFT(G154,2),"00"),"-",TEXT(RIGHT(G154,1),"0"),TEXT(I154,"0"),"-",TEXT(K154,"00")) -> 1-2-2-21-20-00 | N154: =IF(L154="",IF(J154="",IF(H154="",IF(F154="",IF(D154="",B154,D154),F154),H154),J154),L154) -> BIENES INMUEBLES | O154: =IF(P154="",0,IF(M153=M154,IF(O153="",0,O153)+1,"")) -> 2 | P154: PARROQUIA ANTIMANO | Q154: =CONCATENATE(TEXT(A154,"0"),"-",TEXT(C154,"0"),"-",TEXT(E154,"0"),"-",TEXT(LEFT(G154,2),"00"),"-",TEXT(RIGHT(G154,1),"0"),TEXT(I154,"0"),"-",TEXT(K154,"00"),"-",TEXT(O154,"000")) -> 1-2-2-21-20-00-002 | R154: =IF(P154="",IF(L154="",IF(J154="",IF(H154="",IF(F154="",IF(D154="",B154,D154),F154),H154),J154),L154),P154) -> PARROQUIA ANTIMANO
A155: 1 | B155: =VLOOKUP(A155,'ACTIVOS CODIGO'!A:B,2,0) -> ACTIVO | C155: 2 | D155: =VLOOKUP(C155,'ACTIVOS CODIGO'!C:D,2,0) -> ACTIVO DE LA HACIENDA = ACTIVO NO CORRIENTE | E155: 2 | F155: =VLOOKUP(E155,'ACTIVOS CODIGO'!E:F,2,0) -> ACTIVO EXIGIBLE | G155: 212 | H155: =VLOOKUP(G155,'PUB 21'!$A$1:$B$29,2,0) -> BIENES INMUEBLES | M155: =CONCATENATE(TEXT(A155,"0"),"-",TEXT(C155,"0"),"-",TEXT(E155,"0"),"-",TEXT(LEFT(G155,2),"00"),"-",TEXT(RIGHT(G155,1),"0"),TEXT(I155,"0"),"-",TEXT(K155,"00")) -> 1-2-2-21-20-00 | N155: =IF(L155="",IF(J155="",IF(H155="",IF(F155="",IF(D155="",B155,D155),F155),H155),J155),L155) -> BIENES INMUEBLES | O155: =IF(P155="",0,IF(M154=M155,IF(O154="",0,O154)+1,"")) -> 3 | P155: PARROQUIA CANDELARIA | Q155: =CONCATENATE(TEXT(A155,"0"),"-",TEXT(C155,"0"),"-",TEXT(E155,"0"),"-",TEXT(LEFT(G155,2),"00"),"-",TEXT(RIGHT(G155,1),"0"),TEXT(I155,"0"),"-",TEXT(K155,"00"),"-",TEXT(O155,"000")) -> 1-2-2-21-20-00-003 | R155: =IF(P155="",IF(L155="",IF(J155="",IF(H155="",IF(F155="",IF(D155="",B155,D155),F155),H155),J155),L155),P155) -> PARROQUIA CANDELARIA
A156: 1 | B156: =VLOOKUP(A156,'ACTIVOS CODIGO'!A:B,2,0) -> ACTIVO | C156: 2 | D156: =VLOOKUP(C156,'ACTIVOS CODIGO'!C:D,2,0) -> ACTIVO DE LA HACIENDA = ACTIVO NO CORRIENTE | E156: 2 | F156: =VLOOKUP(E156,'ACTIVOS CODIGO'!E:F,2,0) -> ACTIVO EXIGIBLE | G156: 212 | H156: =VLOOKUP(G156,'PUB 21'!$A$1:$B$29,2,0) -> BIENES INMUEBLES | M156: =CONCATENATE(TEXT(A156,"0"),"-",TEXT(C156,"0"),"-",TEXT(E156,"0"),"-",TEXT(LEFT(G156,2),"00"),"-",TEXT(RIGHT(G156,1),"0"),TEXT(I156,"0"),"-",TEXT(K156,"00")) -> 1-2-2-21-20-00 | N156: =IF(L156="",IF(J156="",IF(H156="",IF(F156="",IF(D156="",B156,D156),F156),H156),J156),L156) -> BIENES INMUEBLES | O156: =IF(P156="",0,IF(M155=M156,IF(O155="",0,O155)+1,"")) -> 4 | P156: PARROQUIA CATEDRAL | Q156: =CONCATENATE(TEXT(A156,"0"),"-",TEXT(C156,"0"),"-",TEXT(E156,"0"),"-",TEXT(LEFT(G156,2),"00"),"-",TEXT(RIGHT(G156,1),"0"),TEXT(I156,"0"),"-",TEXT(K156,"00"),"-",TEXT(O156,"000")) -> 1-2-2-21-20-00-004 | R156: =IF(P156="",IF(L156="",IF(J156="",IF(H156="",IF(F156="",IF(D156="",B156,D156),F156),H156),J156),L156),P156) -> PARROQUIA CATEDRAL
A157: 1 | B157: =VLOOKUP(A157,'ACTIVOS CODIGO'!A:B,2,0) -> ACTIVO | C157: 2 | D157: =VLOOKUP(C157,'ACTIVOS CODIGO'!C:D,2,0) -> ACTIVO DE LA HACIENDA = ACTIVO NO CORRIENTE | E157: 2 | F157: =VLOOKUP(E157,'ACTIVOS CODIGO'!E:F,2,0) -> ACTIVO EXIGIBLE | G157: 212 | H157: =VLOOKUP(G157,'PUB 21'!$A$1:$B$29,2,0) -> BIENES INMUEBLES | M157: =CONCATENATE(TEXT(A157,"0"),"-",TEXT(C157,"0"),"-",TEXT(E157,"0"),"-",TEXT(LEFT(G157,2),"00"),"-",TEXT(RIGHT(G157,1),"0"),TEXT(I157,"0"),"-",TEXT(K157,"00")) -> 1-2-2-21-20-00 | N157: =IF(L157="",IF(J157="",IF(H157="",IF(F157="",IF(D157="",B157,D157),F157),H157),J157),L157) -> BIENES INMUEBLES | O157: =IF(P157="",0,IF(M156=M157,IF(O156="",0,O156)+1,"")) -> 5 | P157: PARROQUIA EL RECREO | Q157: =CONCATENATE(TEXT(A157,"0"),"-",TEXT(C157,"0"),"-",TEXT(E157,"0"),"-",TEXT(LEFT(G157,2),"00"),"-",TEXT(RIGHT(G157,1),"0"),TEXT(I157,"0"),"-",TEXT(K157,"00"),"-",TEXT(O157,"000")) -> 1-2-2-21-20-00-005 | R157: =IF(P157="",IF(L157="",IF(J157="",IF(H157="",IF(F157="",IF(D157="",B157,D157),F157),H157),J157),L157),P157) -> PARROQUIA EL RECREO
A158: 1 | B158: =VLOOKUP(A158,'ACTIVOS CODIGO'!A:B,2,0) -> ACTIVO | C158: 2 | D158: =VLOOKUP(C158,'ACTIVOS CODIGO'!C:D,2,0) -> ACTIVO DE LA HACIENDA = ACTIVO NO CORRIENTE | E158: 2 | F158: =VLOOKUP(E158,'ACTIVOS CODIGO'!E:F,2,0) -> ACTIVO EXIGIBLE | G158: 212 | H158: =VLOOKUP(G158,'PUB 21'!$A$1:$B$29,2,0) -> BIENES INMUEBLES | M158: =CONCATENATE(TEXT(A158,"0"),"-",TEXT(C158,"0"),"-",TEXT(E158,"0"),"-",TEXT(LEFT(G158,2),"00"),"-",TEXT(RIGHT(G158,1),"0"),TEXT(I158,"0"),"-",TEXT(K158,"00")) -> 1-2-2-21-20-00 | N158: =IF(L158="",IF(J158="",IF(H158="",IF(F158="",IF(D158="",B158,D158),F158),H158),J158),L158) -> BIENES INMUEBLES | O158: =IF(P158="",0,IF(M157=M158,IF(O157="",0,O157)+1,"")) -> 6 | P158: PARROQUIA EL VALLE | Q158: =CONCATENATE(TEXT(A158,"0"),"-",TEXT(C158,"0"),"-",TEXT(E158,"0"),"-",TEXT(LEFT(G158,2),"00"),"-",TEXT(RIGHT(G158,1),"0"),TEXT(I158,"0"),"-",TEXT(K158,"00"),"-",TEXT(O158,"000")) -> 1-2-2-21-20-00-006 | R158: =IF(P158="",IF(L158="",IF(J158="",IF(H158="",IF(F158="",IF(D158="",B158,D158),F158),H158),J158),L158),P158) -> PARROQUIA EL VALLE
...

Sheet PUB 21
A1: 102 | B1: TESORERIA MUNICIPAL
A2: 110 | B2: FONDOS DEL SITUADO COORDINADO
A3: 120 | B3: DOCUMENTOS NEGOCIABLES
A4: 122 | B4: INGRESOS POR RECAUDAR
A5: 126 | B5: FONDOS EN AVANCE
A6: 128 | B6: FONDOS ANTICIPADOS
A7: 130 | B7: FONDOS ESPECIALES
A8: 132 | B8: FONDOS DE TERCEROS
A9: 200 | B9: SITUACION FISCAL DEL TESORO
A10: 210 | B10: APORTE DE CAPITAL Y ACCIONES
A11: 212 | B11: BIENES INMUEBLES
A12: 214 | B12: BIENES MUEBLES
... A29: 401 | B29: FONDOS BANCOS INTERVENIDOS

Sheet ACTIVOS CODIGO
A1: 1 | B1: ACTIVO | C1: 1 | D1: ACTIVO DEL TESORO = ACTIVO CORRIENTE | E1: 1 | F1: ACTIVO DISPONIBLE | H1: 1 | I1: PASIVO DEL TESORO = PASIVO CORRIENTE | J1: 1 | K1: PASIVO DISPONIBLE
A2: 2 | B2: PASIVO | C2: 2 | D2: ACTIVO DE LA HACIENDA = ACTIVO NO CORRIENTE | E2: 2 | F2: ACTIVO EXIGIBLE | H2: 2 | I2: PASIVO DE LA HACIENDA = PASIVO NO CORRIENTE | J2: 2 | K2: PASIVO EXIGIBLE
A3: 3 | B3: INGRESOS | C3: 3 | D3: INGRESO DE LA HACIENDA
A4: 4 | B4: GASTOS | C4: 4 | D4: CUENTA DE GASTO HACIENDA
A5: 5 | B5: LIQUIDACION DEL PRESUPUESTO | C5: 5 | D5: CUENTA DE RESULTADOS DE LA HACIENDA
A6: 6 | B6: CUENTA DE ORDEN | C6: 6 | D6: BANCO INTERVERNIDO DE LA HACIENDA
C7: 7 | D7: CUENTA DE ORDEN DE LA HACIENDA
